Workbook

Sheet Datadump
A1: Date | B1: Deal Name | C1: Tranche Name | D1: Position | E1: Partnership Name | F1: LP Schedule A Legal Entity | G1: Account Name | H1: LP Schedule A Name | I1: EID (Investment Vehicle) | J1: Investor Currency | K1: Vehicle Name | L1: Transaction Type | M1: Investing Through Feeder | N1: ROC | O1: Return of Excess Capital | P1: ALLOCATED FEES | Q1: RECOUPED LOSS | R1: Gain Before Carried Interest | S1: Carried Interest On Gains | T1: CurrentIncome Before Carried Interest | U1: Carried_Interest_On_CurrentIncome | V1: ROC(USD) | W1: Return of Excess Capital (USD) | X1: Gain(USD) | Y1: Carried Interest on Gains(USD) | Z1: Current Income(USD) | AA1: Carried Interest On CurrentIncome(USD) | AB1: Investment Contribution Rate | AC1: Distribution Exchange Rate | AD1: Interest Paid by Current Income | AE1: Interest Paid by Gain | AF1: Interest Paid by ROC | AG1: Principal Paid by ROC | AH1: Principal Paid by ROC (Reclassified Gain) | AI1: Principal Paid by Gain | AJ1: Principal Paid by Current Income | AK1: CurrrentIncome_After_Interest_Paid | AL1: Gain_After_Interest_Paid | AM1: ROC_After_Interest_andPrincipal_Paid | AN1: ROC_After_Interest_andPrincipal_Paid (Reclassified Gain) | AO1: Partnership Expenses | AP1: 1441 Foreign Tax Withholding | AQ1: 1446 Foreign Tax Withholding | AR1: Corporate Tax Withholding | AS1: State Tax Withholding | AT1: S. NO. | AU1: x | AV1: Deal Name | AW1: BX Access ID | AX1: ROC Proceeds | AY1: AFE | AZ1: Recouped Loss | BA1: Gain | BB1: Income | BC1: Carry | BD1: Total Interest | BE1: Total Principal | BF1: Final ROC | BG1: Final Gain | BH1: Final Income | BI1: Tax Withholding | BJ1: Total Distribution | BK1: ROC Proceeds (USD) | BL1: Gain (USD) | BM1: Income (USD) | BN1: Carry (USD) | BO1: Final ROC (USD) | BP1: Final Gain (USD) | BQ1: Final Income (USD) | BR1: Tax Withholding (USD) | BS1: Total Distribution (USD) | BU1: gg | BV1: -1 | BW1: Tax. With | BX1: Int | BY1: gg | BZ1: Sum of X | CA1: Deal type | CB1: D/E | CC1: LPA Name Change1 | CD1: Concatenate | CE1: Affiliate | CF1: LPA Name Change2 | CG1: Deal Name | CH1: Deal Name | CI1: Deal Name Change | CK1: Unique Investor | CO1: LP Schedule A Name | CV1: LP Schedule A Name | CX1: Deal Name
A2: 45382 | B2: =IFERROR(VLOOKUP(CG2,CH:CI,2,0),CG2) -> Deal 1 | C2: Tranche 1 | D2: Position 1 | E2: Partnership 1 | F2: SCH A Legal Entity 1 | G2: Partner 1 | H2: =IF(CF2<>"",CF2,CC2) -> LP SCH A 1 | I2: Partner ID 1 | J2: USD | K2: Vehicle 1 | L2: Disposition | N2: 0 | O2: 0 | P2: 0 | Q2: 0 | R2: 0 | S2: 0 | T2: 0 | U2: 0 | V2: 0 | W2: 0 | X2: 0 | Y2: 0 | Z2: 0 | AA2: 0 | AB2: 1 | AC2: 1 | AD2: 0 | AE2: 766.1 | AF2: 1245.4 | AG2: 562.89 | AH2: 0 | AI2: 0 | AJ2: 0 | AK2: 0 | AL2: 0 | AM2: 0 | AN2: 0 | AO2: 0 | AP2: 0 | AQ2: 0 | AR2: 0 | AS2: 0 | AT2: =VLOOKUP(H2,Control!B:C,2,0) -> 1 | AV2: =IFERROR(VLOOKUP($B2,'[1]Accounts - MDM Data'!$N$1:$O$5,2,0),$B2) -> Deal 1 | AW2: =VLOOKUP(H2,'[1]Accounts - MDM Data'!$H$2:$I$8,2,FALSE) -> #N/A | AX2: =N2 -> 0 | AY2: =P2 -> 0 | AZ2: =Q2 -> 0 | BA2: =R2 -> 0 | BB2: =T2 -> 0 | BC2: =S2+U2 -> 0 | BD2: =SUM(AD2:AF2) -> 2011.5 | BE2: =SUM(AG2:AI2) -> 562.89 | BF2: =IF($M2="Yes",0,IF(ISNUMBER(SEARCH("LH",F2)),SUM($AM2+$AN2),IF($N2=0,SUM(AF2+AG2+AH2+AM2+AN2),$N2))) -> 1808.29 | BG2: =IF($M2="Yes",0,IF(ISNUMBER(SEARCH("LH",F2)),$AL2,IF(SUM($P2:$S2)=0,SUM(AE2+AI2+AL2),SUM($P2:$S2)))) -> 766.1 | BH2: =IF(M2="yes",0,IF(ISNUMBER(SEARCH("LH",F2)),AK2,IF(SUM(T2+U2)=0,SUM(AD2+AK2),SUM(T2+U2)))) -> 0 | BI2: =ROUND(SUM($AP2:$AS2),2) -> 0 | BJ2: =SUM(BD2:BH2)+SUM(AO2:AS2)+O2 -> 5148.78 | BK2: =ROUND($AX2/$AB2,2) -> 0 | BL2: =ROUND(SUM($AY2:$BA2)/$AC2+($AX2/$AC2-$BK2),2) -> 0 | BM2: =ROUND($BB2/$AC2,2) -> 0 | BN2: =ROUND($BC2/$AC2,2) -> 0 | BO2: =ROUND($BF2/AB2,2) -> 1808.29 | BP2: =ROUND(IF($BL2=0,0,$BL2+IF($S2=0,0,$BN2)),2) -> 0 | BQ2: =ROUND(IF($BM2=0,0,$BM2+IF($U2=0,0,$BN2)),2) -> 0 | BR2: =ROUND(SUM($AP2:$AS2)/$AC2,2) -> 0 | BS2: =SUM(BO2:BR2) -> 1808.29 | BU2: =SUM(AD2:AG2)+SUM(BF2:BH2) -> 5148.78 | BV2: =SUM(N2:U2) -> 0 | BW2: =SUM(AP2:AS2) -> 0 | BX2: =SUM(AD2,AE2,AF2) -> 2011.5 | BY2: =BU2-BV2 -> 5148.78 | BZ2: =N2+P2+Q2+R2+S2+T2+U2 -> 0 | CA2: Domestic | CB2: =IF(SUM(AD2:AJ2)=0,"Equity","Debt") -> Debt | CC2: =IF(RIGHT(CV2,4)="(GP)","General Partners",IF(RIGHT(CV2,5)="(ALP)","GP Excess",CV2)) -> LP SCH A 1 | CD2: =F2&"_"&AV2 -> SCH A Legal Entity 1_Deal 1 | CE2: =B2&"_"&G2&"_"&E2 -> Deal 1_Partner 1_Partnership 1 | CF2: =IFERROR(VLOOKUP(CE2,[1]Mapping!A:E,5,0),"") | CG2: Deal 1 | CO2: =IF(FM2<>"",FM2,FJ2) -> 0 | CV2: LP SCH A 1 | CX2: Deal 1
A3: 45382 | B3: =IFERROR(VLOOKUP(CG3,CH:CI,2,0),CG3) -> Deal 1 | C3: Tranche 1 | D3: Position 1 | E3: Partnership 1 | F3: SCH A Legal Entity 2 | G3: Partner 2 | H3: =IF(CF3<>"",CF3,CC3) -> LP SCH A 2 | I3: Partner ID 2 | J3: USD | K3: Vehicle 2 | L3: Disposition | N3: 0 | O3: 0 | P3: 0 | Q3: 0 | R3: 0 | S3: 0 | T3: 0 | U3: 0 | V3: 0 | W3: 0 | X3: 0 | Y3: 0 | Z3: 0 | AA3: 0 | AB3: 1 | AC3: 1 | AD3: 0 | AE3: 17411.24 | AF3: 28304.55 | AG3: 12793.05 | AH3: 0 | AI3: 0 | AJ3: 0 | AK3: 0 | AL3: 0 | AM3: 0 | AN3: 0 | AO3: 0 | AP3: 0 | AQ3: 0 | AR3: 0 | AS3: 0 | AT3: =VLOOKUP(H3,Control!B:C,2,0) -> 2 | AV3: =IFERROR(VLOOKUP($B3,'[1]Accounts - MDM Data'!$N$1:$O$5,2,0),$B3) -> Deal 1 | AW3: =VLOOKUP(H3,'[1]Accounts - MDM Data'!$H$2:$I$8,2,FALSE) -> #N/A | AX3: =N3 -> 0 | AY3: =P3 -> 0 | AZ3: =Q3 -> 0 | BA3: =R3 -> 0 | BB3: =T3 -> 0 | BC3: =S3+U3 -> 0 | BD3: =SUM(AD3:AF3) -> 45715.79 | BE3: =SUM(AG3:AI3) -> 12793.05 | BF3: =IF($M3="Yes",0,IF(ISNUMBER(SEARCH("LH",F3)),SUM($AM3+$AN3),IF($N3=0,SUM(AF3+AG3+AH3+AM3+AN3),$N3))) -> 41097.6 | BG3: =IF($M3="Yes",0,IF(ISNUMBER(SEARCH("LH",F3)),$AL3,IF(SUM($P3:$S3)=0,SUM(AE3+AI3+AL3),SUM($P3:$S3)))) -> 17411.24 | BH3: =IF(M3="yes",0,IF(ISNUMBER(SEARCH("LH",F3)),AK3,IF(SUM(T3+U3)=0,SUM(AD3+AK3),SUM(T3+U3)))) -> 0 | BI3: =ROUND(SUM($AP3:$AS3),2) -> 0 | BJ3: =SUM(BD3:BH3)+SUM(AO3:AS3)+O3 -> 117017.68 | BK3: =ROUND($AX3/$AB3,2) -> 0 | BL3: =ROUND(SUM($AY3:$BA3)/$AC3+($AX3/$AC3-$BK3),2) -> 0 | BM3: =ROUND($BB3/$AC3,2) -> 0 | BN3: =ROUND($BC3/$AC3,2) -> 0 | BO3: =ROUND($BF3/AB3,2) -> 41097.6 | BP3: =ROUND(IF($BL3=0,0,$BL3+IF($S3=0,0,$BN3)),2) -> 0 | BQ3: =ROUND(IF($BM3=0,0,$BM3+IF($U3=0,0,$BN3)),2) -> 0 | BR3: =ROUND(SUM($AP3:$AS3)/$AC3,2) -> 0 | BS3: =SUM(BO3:BR3) -> 41097.6 | BU3: =SUM(AD3:AG3)+SUM(BF3:BH3) -> 117017.68 | BV3: =SUM(N3:U3) -> 0 | BW3: =SUM(AP3:AS3) -> 0 | BX3: =SUM(AD3,AE3,AF3) -> 45715.79 | BY3: =BU3-BV3 -> 117017.68 | BZ3: =N3+P3+Q3+R3+S3+T3+U3 -> 0 | CA3: Domestic | CB3: =IF(SUM(AD3:AJ3)=0,"Equity","Debt") -> Debt | CC3: =IF(RIGHT(CV3,4)="(GP)","General Partners",IF(RIGHT(CV3,5)="(ALP)","GP Excess",CV3)) -> LP SCH A 2 | CD3: =F3&"_"&AV3 -> SCH A Legal Entity 2_Deal 1 | CE3: =B3&"_"&G3&"_"&E3 -> Deal 1_Partner 2_Partnership 1 | CF3: =IFERROR(VLOOKUP(CE3,[1]Mapping!A:E,5,0),"") | CG3: Deal 1 | CO3: =IF(FM3<>"",FM3,FJ3) -> 0 | CV3: LP SCH A 2 | CX3: Deal 1
A4: 45382 | B4: =IFERROR(VLOOKUP(CG4,CH:CI,2,0),CG4) -> Deal 1 | C4: Tranche 1 | D4: Position 1 | E4: Partnership 1 | F4: SCH A Legal Entity 3 | G4: Partner 3 | H4: =IF(CF4<>"",CF4,CC4) -> LP SCH A 3 | I4: Partner ID 3 | J4: USD | K4: Vehicle 3 | L4: Disposition | N4: 0 | O4: 0 | P4: 0 | Q4: 0 | R4: 0 | S4: 0 | T4: 0 | U4: 0 | V4: 0 | W4: 0 | X4: 0 | Y4: 0 | Z4: 0 | AA4: 0 | AB4: 1 | AC4: 1 | AD4: 0 | AE4: 5975.54 | AF4: 9714.03 | AG4: 4390.66 | AH4: 0 | AI4: 0 | AJ4: 0 | AK4: 0 | AL4: 0 | AM4: 0 | AN4: 0 | AO4: 0 | AP4: 0 | AQ4: 0 | AR4: 0 | AS4: 0 | AT4: =VLOOKUP(H4,Control!B:C,2,0) -> 3 | AV4: =IFERROR(VLOOKUP($B4,'[1]Accounts - MDM Data'!$N$1:$O$5,2,0),$B4) -> Deal 1 | AW4: =VLOOKUP(H4,'[1]Accounts - MDM Data'!$H$2:$I$8,2,FALSE) -> #N/A | AX4: =N4 -> 0 | AY4: =P4 -> 0 | AZ4: =Q4 -> 0 | BA4: =R4 -> 0 | BB4: =T4 -> 0 | BC4: =S4+U4 -> 0 | BD4: =SUM(AD4:AF4) -> 15689.57 | BE4: =SUM(AG4:AI4) -> 4390.66 | BF4: =IF($M4="Yes",0,IF(ISNUMBER(SEARCH("LH",F4)),SUM($AM4+$AN4),IF($N4=0,SUM(AF4+AG4+AH4+AM4+AN4),$N4))) -> 14104.69 | BG4: =IF($M4="Yes",0,IF(ISNUMBER(SEARCH("LH",F4)),$AL4,IF(SUM($P4:$S4)=0,SUM(AE4+AI4+AL4),SUM($P4:$S4)))) -> 5975.54 | BH4: =IF(M4="yes",0,IF(ISNUMBER(SEARCH("LH",F4)),AK4,IF(SUM(T4+U4)=0,SUM(AD4+AK4),SUM(T4+U4)))) -> 0 | BI4: =ROUND(SUM($AP4:$AS4),2) -> 0 | BJ4: =SUM(BD4:BH4)+SUM(AO4:AS4)+O4 -> 40160.46 | BK4: =ROUND($AX4/$AB4,2) -> 0 | BL4: =ROUND(SUM($AY4:$BA4)/$AC4+($AX4/$AC4-$BK4),2) -> 0 | BM4: =ROUND($BB4/$AC4,2) -> 0 | BN4: =ROUND($BC4/$AC4,2) -> 0 | BO4: =ROUND($BF4/AB4,2) -> 14104.69 | BP4: =ROUND(IF($BL4=0,0,$BL4+IF($S4=0,0,$BN4)),2) -> 0 | BQ4: =ROUND(IF($BM4=0,0,$BM4+IF($U4=0,0,$BN4)),2) -> 0 | BR4: =ROUND(SUM($AP4:$AS4)/$AC4,2) -> 0 | BS4: =SUM(BO4:BR4) -> 14104.69 | BU4: =SUM(AD4:AG4)+SUM(BF4:BH4) -> 40160.46 | BV4: =SUM(N4:U4) -> 0 | BW4: =SUM(AP4:AS4) -> 0 | BX4: =SUM(AD4,AE4,AF4) -> 15689.57 | BY4: =BU4-BV4 -> 40160.46 | BZ4: =N4+P4+Q4+R4+S4+T4+U4 -> 0 | CA4: Domestic | CB4: =IF(SUM(AD4:AJ4)=0,"Equity","Debt") -> Debt | CC4: =IF(RIGHT(CV4,4)="(GP)","General Partners",IF(RIGHT(CV4,5)="(ALP)","GP Excess",CV4)) -> LP SCH A 3 | CD4: =F4&"_"&AV4 -> SCH A Legal Entity 3_Deal 1 | CE4: =B4&"_"&G4&"_"&E4 -> Deal 1_Partner 3_Partnership 1 | CF4: =IFERROR(VLOOKUP(CE4,[1]Mapping!A:E,5,0),"") | CG4: Deal 1 | CO4: =IF(FM4<>"",FM4,FJ4) -> 0 | CV4: LP SCH A 3 | CX4: Deal 1
A5: 45382 | B5: =IFERROR(VLOOKUP(CG5,CH:CI,2,0),CG5) -> Deal 1 | C5: Tranche 1 | D5: Position 1 | E5: Partnership 2 | F5: SCH A Legal Entity 4 | G5: Partner 4 | H5: =IF(CF5<>"",CF5,CC5) -> LP SCH A 4 | I5: Partner ID 4 | J5: USD | K5: Vehicle 4 | L5: Disposition | N5: 16439.04 | O5: 0 | P5: 6964.5 | Q5: 0 | R5: 0 | S5: 0 | T5: 0 | U5: 0 | V5: 16439.04 | W5: 0 | X5: 6964.5 | Y5: 0 | Z5: 0 | AA5: 0 | AB5: 1 | AC5: 1 | AD5: 0 | AE5: 0 | AF5: 0 | AG5: 0 | AH5: 0 | AI5: 0 | AJ5: 0 | AK5: 0 | AL5: 6964.5 | AM5: 16439.04 | AN5: 0 | AO5: 0 | AP5: 0 | AQ5: 0 | AR5: 0 | AS5: 0 | AT5: =VLOOKUP(H5,Control!B:C,2,0) -> 4 | AV5: =IFERROR(VLOOKUP($B5,'[1]Accounts - MDM Data'!$N$1:$O$5,2,0),$B5) -> Deal 1 | AW5: =VLOOKUP(H5,'[1]Accounts - MDM Data'!$H$2:$I$8,2,FALSE) -> #N/A | AX5: =N5 -> 16439.04 | AY5: =P5 -> 6964.5 | AZ5: =Q5 -> 0 | BA5: =R5 -> 0 | BB5: =T5 -> 0 | BC5: =S5+U5 -> 0 | BD5: =SUM(AD5:AF5) -> 0 | BE5: =SUM(AG5:AI5) -> 0 | BF5: =IF($M5="Yes",0,IF(ISNUMBER(SEARCH("LH",F5)),SUM($AM5+$AN5),IF($N5=0,SUM(AF5+AG5+AH5+AM5+AN5),$N5))) -> 16439.04 | BG5: =IF($M5="Yes",0,IF(ISNUMBER(SEARCH("LH",F5)),$AL5,IF(SUM($P5:$S5)=0,SUM(AE5+AI5+AL5),SUM($P5:$S5)))) -> 6964.5 | BH5: =IF(M5="yes",0,IF(ISNUMBER(SEARCH("LH",F5)),AK5,IF(SUM(T5+U5)=0,SUM(AD5+AK5),SUM(T5+U5)))) -> 0 | BI5: =ROUND(SUM($AP5:$AS5),2) -> 0 | BJ5: =SUM(BD5:BH5)+SUM(AO5:AS5)+O5 -> 23403.54 | BK5: =ROUND($AX5/$AB5,2) -> 16439.04 | BL5: =ROUND(SUM($AY5:$BA5)/$AC5+($AX5/$AC5-$BK5),2) -> 6964.5 | BM5: =ROUND($BB5/$AC5,2) -> 0 | BN5: =ROUND($BC5/$AC5,2) -> 0 | BO5: =ROUND($BF5/AB5,2) -> 16439.04 | BP5: =ROUND(IF($BL5=0,0,$BL5+IF($S5=0,0,$BN5)),2) -> 6964.5 | BQ5: =ROUND(IF($BM5=0,0,$BM5+IF($U5=0,0,$BN5)),2) -> 0 | BR5: =ROUND(SUM($AP5:$AS5)/$AC5,2) -> 0 | BS5: =SUM(BO5:BR5) -> 23403.54 | BU5: =SUM(AD5:AG5)+SUM(BF5:BH5) -> 23403.54 | BV5: =SUM(N5:U5) -> 23403.54 | BW5: =SUM(AP5:AS5) -> 0 | BX5: =SUM(AD5,AE5,AF5) -> 0 | BY5: =BU5-BV5 -> 0 | BZ5: =N5+P5+Q5+R5+S5+T5+U5 -> 23403.54 | CA5: Domestic | CB5: =IF(SUM(AD5:AJ5)=0,"Equity","Debt") -> Equity | CC5: =IF(RIGHT(CV5,4)="(GP)","General Partners",IF(RIGHT(CV5,5)="(ALP)","GP Excess",CV5)) -> LP SCH A 4 | CD5: =F5&"_"&AV5 -> SCH A Legal Entity 4_Deal 1 | CE5: =B5&"_"&G5&"_"&E5 -> Deal 1_Partner 4_Partnership 2 | CF5: =IFERROR(VLOOKUP(CE5,[1]Mapping!A:E,5,0),"") | CG5: Deal 1 | CO5: =IF(FM5<>"",FM5,FJ5) -> 0 | CV5: LP SCH A 4 | CX5: Deal 1
A6: 45382 | B6: =IFERROR(VLOOKUP(CG6,CH:CI,2,0),CG6) -> Deal 1 | C6: Tranche 1 | D6: Position 1 | E6: Partnership 2 | F6: SCH A Legal Entity 4 | G6: Partner 5 | H6: =IF(CF6<>"",CF6,CC6) -> LP SCH A 5 | I6: Partner ID 4 | J6: USD | K6: Vehicle 4 | L6: Disposition | N6: 2396.81 | O6: 0 | P6: 1015.43 | Q6: 0 | R6: 0 | S6: 0 | T6: 0 | U6: 0 | V6: 2396.81 | W6: 0 | X6: 1015.43 | Y6: 0 | Z6: 0 | AA6: 0 | AB6: 1 | AC6: 1 | AD6: 0 | AE6: 0 | AF6: 0 | AG6: 0 | AH6: 0 | AI6: 0 | AJ6: 0 | AK6: 0 | AL6: 1015.43 | AM6: 2396.81 | AN6: 0 | AO6: 0 | AP6: 0 | AQ6: 0 | AR6: 0 | AS6: 0 | AT6: =VLOOKUP(H6,Control!B:C,2,0) -> 5 | AV6: =IFERROR(VLOOKUP($B6,'[1]Accounts - MDM Data'!$N$1:$O$5,2,0),$B6) -> Deal 1 | AW6: =VLOOKUP(H6,'[1]Accounts - MDM Data'!$H$2:$I$8,2,FALSE) -> #N/A | AX6: =N6 -> 2396.81 | AY6: =P6 -> 1015.43 | AZ6: =Q6 -> 0 | BA6: =R6 -> 0 | BB6: =T6 -> 0 | BC6: =S6+U6 -> 0 | BD6: =SUM(AD6:AF6) -> 0 | BE6: =SUM(AG6:AI6) -> 0 | BF6: =IF($M6="Yes",0,IF(ISNUMBER(SEARCH("LH",F6)),SUM($AM6+$AN6),IF($N6=0,SUM(AF6+AG6+AH6+AM6+AN6),$N6))) -> 2396.81 | BG6: =IF($M6="Yes",0,IF(ISNUMBER(SEARCH("LH",F6)),$AL6,IF(SUM($P6:$S6)=0,SUM(AE6+AI6+AL6),SUM($P6:$S6)))) -> 1015.43 | BH6: =IF(M6="yes",0,IF(ISNUMBER(SEARCH("LH",F6)),AK6,IF(SUM(T6+U6)=0,SUM(AD6+AK6),SUM(T6+U6)))) -> 0 | BI6: =ROUND(SUM($AP6:$AS6),2) -> 0 | BJ6: =SUM(BD6:BH6)+SUM(AO6:AS6)+O6 -> 3412.24 | BK6: =ROUND($AX6/$AB6,2) -> 2396.81 | BL6: =ROUND(SUM($AY6:$BA6)/$AC6+($AX6/$AC6-$BK6),2) -> 1015.43 | BM6: =ROUND($BB6/$AC6,2) -> 0 | BN6: =ROUND($BC6/$AC6,2) -> 0 | BO6: =ROUND($BF6/AB6,2) -> 2396.81 | BP6: =ROUND(IF($BL6=0,0,$BL6+IF($S6=0,0,$BN6)),2) -> 1015.43 | BQ6: =ROUND(IF($BM6=0,0,$BM6+IF($U6=0,0,$BN6)),2) -> 0 | BR6: =ROUND(SUM($AP6:$AS6)/$AC6,2) -> 0 | BS6: =SUM(BO6:BR6) -> 3412.24 | BU6: =SUM(AD6:AG6)+SUM(BF6:BH6) -> 3412.24 | BV6: =SUM(N6:U6) -> 3412.24 | BW6: =SUM(AP6:AS6) -> 0 | BX6: =SUM(AD6,AE6,AF6) -> 0 | BY6: =BU6-BV6 -> 0 | BZ6: =N6+P6+Q6+R6+S6+T6+U6 -> 3412.24 | CA6: Domestic | CB6: =IF(SUM(AD6:AJ6)=0,"Equity","Debt") -> Equity | CC6: =IF(RIGHT(CV6,4)="(GP)","General Partners",IF(RIGHT(CV6,5)="(ALP)","GP Excess",CV6)) -> LP SCH A 5 | CD6: =F6&"_"&AV6 -> SCH A Legal Entity 4_Deal 1 | CE6: =B6&"_"&G6&"_"&E6 -> Deal 1_Partner 5_Partnership 2 | CF6: =IFERROR(VLOOKUP(CE6,[1]Mapping!A:E,5,0),"") | CG6: Deal 1 | CO6: =IF(FM6<>"",FM6,FJ6) -> 0 | CV6: LP SCH A 5 | CX6: Deal 1
A7: 45382 | B7: =IFERROR(VLOOKUP(CG7,CH:CI,2,0),CG7) -> Deal 1 | C7: Tranche 1 | D7: Position 1 | E7: Partnership 3 | F7: SCH A Legal Entity 5 | G7: Partner 6 | H7: =IF(CF7<>"",CF7,CC7) -> LP SCH A 6 | I7: Partner ID 5 | J7: USD | K7: Vehicle 5 | L7: Disposition | N7: 2876.83 | O7: 0 | P7: 1218.79 | Q7: 0 | R7: 0 | S7: 0 | T7: 0 | U7: 0 | V7: 2876.83 | W7: 0 | X7: 1218.79 | Y7: 0 | Z7: 0 | AA7: 0 | AB7: 1 | AC7: 1 | AD7: 0 | AE7: 0 | AF7: 0 | AG7: 0 | AH7: 0 | AI7: 0 | AJ7: 0 | AK7: 0 | AL7: 1218.79 | AM7: 2876.83 | AN7: 0 | AO7: 0 | AP7: 0 | AQ7: 0 | AR7: 0 | AS7: 0 | AT7: =VLOOKUP(H7,Control!B:C,2,0) -> 6 | AV7: =IFERROR(VLOOKUP($B7,'[1]Accounts - MDM Data'!$N$1:$O$5,2,0),$B7) -> Deal 1 | AW7: =VLOOKUP(H7,'[1]Accounts - MDM Data'!$H$2:$I$8,2,FALSE) -> #N/A | AX7: =N7 -> 2876.83 | AY7: =P7 -> 1218.79 | AZ7: =Q7 -> 0 | BA7: =R7 -> 0 | BB7: =T7 -> 0 | BC7: =S7+U7 -> 0 | BD7: =SUM(AD7:AF7) -> 0 | BE7: =SUM(AG7:AI7) -> 0 | BF7: =IF($M7="Yes",0,IF(ISNUMBER(SEARCH("LH",F7)),SUM($AM7+$AN7),IF($N7=0,SUM(AF7+AG7+AH7+AM7+AN7),$N7))) -> 2876.83 | BG7: =IF($M7="Yes",0,IF(ISNUMBER(SEARCH("LH",F7)),$AL7,IF(SUM($P7:$S7)=0,SUM(AE7+AI7+AL7),SUM($P7:$S7)))) -> 1218.79 | BH7: =IF(M7="yes",0,IF(ISNUMBER(SEARCH("LH",F7)),AK7,IF(SUM(T7+U7)=0,SUM(AD7+AK7),SUM(T7+U7)))) -> 0 | BI7: =ROUND(SUM($AP7:$AS7),2) -> 0 | BJ7: =SUM(BD7:BH7)+SUM(AO7:AS7)+O7 -> 4095.62 | BK7: =ROUND($AX7/$AB7,2) -> 2876.83 | BL7: =ROUND(SUM($AY7:$BA7)/$AC7+($AX7/$AC7-$BK7),2) -> 1218.79 | BM7: =ROUND($BB7/$AC7,2) -> 0 | BN7: =ROUND($BC7/$AC7,2) -> 0 | BO7: =ROUND($BF7/AB7,2) -> 2876.83 | BP7: =ROUND(IF($BL7=0,0,$BL7+IF($S7=0,0,$BN7)),2) -> 1218.79 | BQ7: =ROUND(IF($BM7=0,0,$BM7+IF($U7=0,0,$BN7)),2) -> 0 | BR7: =ROUND(SUM($AP7:$AS7)/$AC7,2) -> 0 | BS7: =SUM(BO7:BR7) -> 4095.62 | BU7: =SUM(AD7:AG7)+SUM(BF7:BH7) -> 4095.62 | BV7: =SUM(N7:U7) -> 4095.62 | BW7: =SUM(AP7:AS7) -> 0 | BX7: =SUM(AD7,AE7,AF7) -> 0 | BY7: =BU7-BV7 -> 0 | BZ7: =N7+P7+Q7+R7+S7+T7+U7 -> 4095.62 | CA7: Domestic | CB7: =IF(SUM(AD7:AJ7)=0,"Equity","Debt") -> Equity | CC7: =IF(RIGHT(CV7,4)="(GP)","General Partners",IF(RIGHT(CV7,5)="(ALP)","GP Excess",CV7)) -> LP SCH A 6 | CD7: =F7&"_"&AV7 -> SCH A Legal Entity 5_Deal 1 | CE7: =B7&"_"&G7&"_"&E7 -> Deal 1_Partner 6_Partnership 3 | CF7: =IFERROR(VLOOKUP(CE7,[1]Mapping!A:E,5,0),"") | CG7: Deal 1 | CO7: =IF(FM7<>"",FM7,FJ7) -> 0 | CV7: LP SCH A 6 | CX7: Deal 1
A8: 45382 | B8: =IFERROR(VLOOKUP(CG8,CH:CI,2,0),CG8) -> Deal 1 | C8: Tranche 1 | D8: Position 1 | E8: Partnership 2 | F8: SCH A Legal Entity 4 | G8: Partner 7 | H8: =IF(CF8<>"",CF8,CC8) -> LP SCH A 7 | I8: Partner ID 4 | J8: USD | K8: Vehicle 4 | L8: Disposition | N8: 1232.93 | O8: 0 | P8: 522.34 | Q8: 0 | R8: 0 | S8: 0 | T8: 0 | U8: 0 | V8: 1232.93 | W8: 0 | X8: 522.34 | Y8: 0 | Z8: 0 | AA8: 0 | AB8: 1 | AC8: 1 | AD8: 0 | AE8: 0 | AF8: 0 | AG8: 0 | AH8: 0 | AI8: 0 | AJ8: 0 | AK8: 0 | AL8: 522.34 | AM8: 1232.93 | AN8: 0 | AO8: 0 | AP8: 0 | AQ8: 0 | AR8: 0 | AS8: 0 | AT8: =VLOOKUP(H8,Control!B:C,2,0) -> 7 | AV8: =IFERROR(VLOOKUP($B8,'[1]Accounts - MDM Data'!$N$1:$O$5,2,0),$B8) -> Deal 1 | AW8: =VLOOKUP(H8,'[1]Accounts - MDM Data'!$H$2:$I$8,2,FALSE) -> #N/A | AX8: =N8 -> 1232.93 | AY8: =P8 -> 522.34 | AZ8: =Q8 -> 0 | BA8: =R8 -> 0 | BB8: =T8 -> 0 | BC8: =S8+U8 -> 0 | BD8: =SUM(AD8:AF8) -> 0 | BE8: =SUM(AG8:AI8) -> 0 | BF8: =IF($M8="Yes",0,IF(ISNUMBER(SEARCH("LH",F8)),SUM($AM8+$AN8),IF($N8=0,SUM(AF8+AG8+AH8+AM8+AN8),$N8))) -> 1232.93 | BG8: =IF($M8="Yes",0,IF(ISNUMBER(SEARCH("LH",F8)),$AL8,IF(SUM($P8:$S8)=0,SUM(AE8+AI8+AL8),SUM($P8:$S8)))) -> 522.34 | BH8: =IF(M8="yes",0,IF(ISNUMBER(SEARCH("LH",F8)),AK8,IF(SUM(T8+U8)=0,SUM(AD8+AK8),SUM(T8+U8)))) -> 0 | BI8: =ROUND(SUM($AP8:$AS8),2) -> 0 | BJ8: =SUM(BD8:BH8)+SUM(AO8:AS8)+O8 -> 1755.27 | BK8: =ROUND($AX8/$AB8,2) -> 1232.93 | BL8: =ROUND(SUM($AY8:$BA8)/$AC8+($AX8/$AC8-$BK8),2) -> 522.34 | BM8: =ROUND($BB8/$AC8,2) -> 0 | BN8: =ROUND($BC8/$AC8,2) -> 0 | BO8: =ROUND($BF8/AB8,2) -> 1232.93 | BP8: =ROUND(IF($BL8=0,0,$BL8+IF($S8=0,0,$BN8)),2) -> 522.34 | BQ8: =ROUND(IF($BM8=0,0,$BM8+IF($U8=0,0,$BN8)),2) -> 0 | BR8: =ROUND(SUM($AP8:$AS8)/$AC8,2) -> 0 | BS8: =SUM(BO8:BR8) -> 1755.27 | BU8: =SUM(AD8:AG8)+SUM(BF8:BH8) -> 1755.27 | BV8: =SUM(N8:U8) -> 1755.27 | BW8: =SUM(AP8:AS8) -> 0 | BX8: =SUM(AD8,AE8,AF8) -> 0 | BY8: =BU8-BV8 -> 0 | BZ8: =N8+P8+Q8+R8+S8+T8+U8 -> 1755.27 | CA8: Domestic | CB8: =IF(SUM(AD8:AJ8)=0,"Equity","Debt") -> Equity | CC8: =IF(RIGHT(CV8,4)="(GP)","General Partners",IF(RIGHT(CV8,5)="(ALP)","GP Excess",CV8)) -> LP SCH A 7 | CD8: =F8&"_"&AV8 -> SCH A Legal Entity 4_Deal 1 | CE8: =B8&"_"&G8&"_"&E8 -> Deal 1_Partner 7_Partnership 2 | CF8: =IFERROR(VLOOKUP(CE8,[1]Mapping!A:E,5,0),"") | CG8: Deal 1 | CO8: =IF(FM8<>"",FM8,FJ8) -> 0 | CV8: LP SCH A 7 | CX8: Deal 1
A9: 45382 | B9: =IFERROR(VLOOKUP(CG9,CH:CI,2,0),CG9) -> Deal 1 | C9: Tranche 1 | D9: Position 1 | E9: Partnership 4 | F9: SCH A Legal Entity 6 | G9: Partner 1 | H9: =IF(CF9<>"",CF9,CC9) -> LP SCH A 1 | I9: Partner ID 6 | J9: USD | K9: Vehicle 6 | L9: Disposition | M9: Yes | N9: 1808.29 | O9: 0 | P9: 766.1 | Q9: 0 | R9: 0 | S9: 0 | T9: 0 | U9: 0 | V9: 1808.29 | W9: 0 | X9: 766.1 | Y9: 0 | Z9: 0 | AA9: 0 | AB9: 1 | AC9: 1 | AD9: 0 | AE9: 0 | AF9: 0 | AG9: 0 | AH9: 0 | AI9: 0 | AJ9: 0 | AK9: 0 | AL9: 0 | AM9: 0 | AN9: 0 | AO9: 0 | AP9: 0 | AQ9: 0 | AR9: 0 | AS9: 0 | AT9: =VLOOKUP(H9,Control!B:C,2,0) -> 1 | AV9: =IFERROR(VLOOKUP($B9,'[1]Accounts - MDM Data'!$N$1:$O$5,2,0),$B9) -> Deal 1 | AW9: =VLOOKUP(H9,'[1]Accounts - MDM Data'!$H$2:$I$8,2,FALSE) -> #N/A | AX9: =N9 -> 1808.29 | AY9: =P9 -> 766.1 | AZ9: =Q9 -> 0 | BA9: =R9 -> 0 | BB9: =T9 -> 0 | BC9: =S9+U9 -> 0 | BD9: =SUM(AD9:AF9) -> 0 | BE9: =SUM(AG9:AI9) -> 0 | BF9: =IF($M9="Yes",0,IF(ISNUMBER(SEARCH("LH",F9)),SUM($AM9+$AN9),IF($N9=0,SUM(AF9+AG9+AH9+AM9+AN9),$N9))) -> 0 | BG9: =IF($M9="Yes",0,IF(ISNUMBER(SEARCH("LH",F9)),$AL9,IF(SUM($P9:$S9)=0,SUM(AE9+AI9+AL9),SUM($P9:$S9)))) -> 0 | BH9: =IF(M9="yes",0,IF(ISNUMBER(SEARCH("LH",F9)),AK9,IF(SUM(T9+U9)=0,SUM(AD9+AK9),SUM(T9+U9)))) -> 0 | BI9: =ROUND(SUM($AP9:$AS9),2) -> 0 | BJ9: =SUM(BD9:BH9)+SUM(AO9:AS9)+O9 -> 0 | BK9: =ROUND($AX9/$AB9,2) -> 1808.29 | BL9: =ROUND(SUM($AY9:$BA9)/$AC9+($AX9/$AC9-$BK9),2) -> 766.1 | BM9: =ROUND($BB9/$AC9,2) -> 0 | BN9: =ROUND($BC9/$AC9,2) -> 0 | BO9: =ROUND($BF9/AB9,2) -> 0 | BP9: =ROUND(IF($BL9=0,0,$BL9+IF($S9=0,0,$BN9)),2) -> 766.1 | BQ9: =ROUND(IF($BM9=0,0,$BM9+IF($U9=0,0,$BN9)),2) -> 0 | BR9: =ROUND(SUM($AP9:$AS9)/$AC9,2) -> 0 | BS9: =SUM(BO9:BR9) -> 766.1 | BU9: =SUM(AD9:AG9)+SUM(BF9:BH9) -> 0 | BV9: =SUM(N9:U9) -> 2574.39 | BW9: =SUM(AP9:AS9) -> 0 | BX9: =SUM(AD9,AE9,AF9) -> 0 | BY9: =BU9-BV9 -> -2574.39 | BZ9: =N9+P9+Q9+R9+S9+T9+U9 -> 2574.39 | CA9: Domestic | CB9: =IF(SUM(AD9:AJ9)=0,"Equity","Debt") -> Equity | CC9: =IF(RIGHT(CV9,4)="(GP)","General Partners",IF(RIGHT(CV9,5)="(ALP)","GP Excess",CV9)) -> LP SCH A 1 | CD9: =F9&"_"&AV9 -> SCH A Legal Entity 6_Deal 1 | CE9: =B9&"_"&G9&"_"&E9 -> Deal 1_Partner 1_Partnership 4 | CF9: =IFERROR(VLOOKUP(CE9,[1]Mapping!A:E,5,0),"") | CG9: Deal 1 | CO9: =IF(FM9<>"",FM9,FJ9) -> 0 | CV9: LP SCH A 1 | CX9: Deal 1
A10: 45382 | B10: =IFERROR(VLOOKUP(CG10,CH:CI,2,0),CG10) -> Deal 1 | C10: Tranche 1 | D10: Position 1 | E10: Partnership 4 | F10: SCH A Legal Entity 6 | G10: Partner 2 | H10: =IF(CF10<>"",CF10,CC10) -> LP SCH A 2 | I10: Partner ID 6 | J10: USD | K10: Vehicle 6 | L10: Disposition | M10: Yes | N10: 41097.6 | O10: 0 | P10: 17411.24 | Q10: 0 | R10: 0 | S10: 0 | T10: 0 | U10: 0 | V10: 41097.6 | W10: 0 | X10: 17411.24 | Y10: 0 | Z10: 0 | AA10: 0 | AB10: 1 | AC10: 1 | AD10: 0 | AE10: 0 | AF10: 0 | AG10: 0 | AH10: 0 | AI10: 0 | AJ10: 0 | AK10: 0 | AL10: 0 | AM10: 0 | AN10: 0 | AO10: 0 | AP10: 0 | AQ10: 0 | AR10: 0 | AS10: 0 | AT10: =VLOOKUP(H10,Control!B:C,2,0) -> 2 | AV10: =IFERROR(VLOOKUP($B10,'[1]Accounts - MDM Data'!$N$1:$O$5,2,0),$B10) -> Deal 1 | AW10: =VLOOKUP(H10,'[1]Accounts - MDM Data'!$H$2:$I$8,2,FALSE) -> #N/A | AX10: =N10 -> 41097.6 | AY10: =P10 -> 17411.24 | AZ10: =Q10 -> 0 | BA10: =R10 -> 0 | BB10: =T10 -> 0 | BC10: =S10+U10 -> 0 | BD10: =SUM(AD10:AF10) -> 0 | BE10: =SUM(AG10:AI10) -> 0 | BF10: =IF($M10="Yes",0,IF(ISNUMBER(SEARCH("LH",F10)),SUM($AM10+$AN10),IF($N10=0,SUM(AF10+AG10+AH10+AM10+AN10),$N10))) -> 0 | BG10: =IF($M10="Yes",0,IF(ISNUMBER(SEARCH("LH",F10)),$AL10,IF(SUM($P10:$S10)=0,SUM(AE10+AI10+AL10),SUM($P10:$S10)))) -> 0 | BH10: =IF(M10="yes",0,IF(ISNUMBER(SEARCH("LH",F10)),AK10,IF(SUM(T10+U10)=0,SUM(AD10+AK10),SUM(T10+U10)))) -> 0 | BI10: =ROUND(SUM($AP10:$AS10),2) -> 0 | BJ10: =SUM(BD10:BH10)+SUM(AO10:AS10)+O10 -> 0 | BK10: =ROUND($AX10/$AB10,2) -> 41097.6 | BL10: =ROUND(SUM($AY10:$BA10)/$AC10+($AX10/$AC10-$BK10),2) -> 17411.24 | BM10: =ROUND($BB10/$AC10,2) -> 0 | BN10: =ROUND($BC10/$AC10,2) -> 0 | BO10: =ROUND($BF10/AB10,2) -> 0 | BP10: =ROUND(IF($BL10=0,0,$BL10+IF($S10=0,0,$BN10)),2) -> 17411.24 | BQ10: =ROUND(IF($BM10=0,0,$BM10+IF($U10=0,0,$BN10)),2) -> 0 | BR10: =ROUND(SUM($AP10:$AS10)/$AC10,2) -> 0 | BS10: =SUM(BO10:BR10) -> 17411.24 | BU10: =SUM(AD10:AG10)+SUM(BF10:BH10) -> 0 | BV10: =SUM(N10:U10) -> 58508.84 | BW10: =SUM(AP10:AS10) -> 0 | BX10: =SUM(AD10,AE10,AF10) -> 0 | BY10: =BU10-BV10 -> -58508.84 | BZ10: =N10+P10+Q10+R10+S10+T10+U10 -> 58508.84 | CA10: Domestic | CB10: =IF(SUM(AD10:AJ10)=0,"Equity","Debt") -> Equity | CC10: =IF(RIGHT(CV10,4)="(GP)","General Partners",IF(RIGHT(CV10,5)="(ALP)","GP Excess",CV10)) -> LP SCH A 2 | CD10: =F10&"_"&AV10 -> SCH A Legal Entity 6_Deal 1 | CE10: =B10&"_"&G10&"_"&E10 -> Deal 1_Partner 2_Partnership 4 | CF10: =IFERROR(VLOOKUP(CE10,[1]Mapping!A:E,5,0),"") | CG10: Deal 1 | CO10: =IF(FM10<>"",FM10,FJ10) -> 0 | CV10: LP SCH A 2 | CX10: Deal 1
A11: 45382 | B11: =IFERROR(VLOOKUP(CG11,CH:CI,2,0),CG11) -> Deal 1 | C11: Tranche 1 | D11: Position 1 | E11: Partnership 5 | F11: SCH A Legal Entity 6 | G11: Partner 3 | H11: =IF(CF11<>"",CF11,CC11) -> LP SCH A 3 | I11: Partner ID 6 | J11: USD | K11: Vehicle 6 | L11: Disposition | M11: Yes | N11: 14104.69 | O11: 0 | P11: 5975.54 | Q11: 0 | R11: 0 | S11: 0 | T11: 0 | U11: 0 | V11: 14104.69 | W11: 0 | X11: 5975.54 | Y11: 0 | Z11: 0 | AA11: 0 | AB11: 1 | AC11: 1 | AD11: 0 | AE11: 0 | AF11: 0 | AG11: 0 | AH11: 0 | AI11: 0 | AJ11: 0 | AK11: 0 | AL11: 0 | AM11: 0 | AN11: 0 | AO11: 0 | AP11: 0 | AQ11: 0 | AR11: 0 | AS11: 0 | AT11: =VLOOKUP(H11,Control!B:C,2,0) -> 3 | AV11: =IFERROR(VLOOKUP($B11,'[1]Accounts - MDM Data'!$N$1:$O$5,2,0),$B11) -> Deal 1 | AW11: =VLOOKUP(H11,'[1]Accounts - MDM Data'!$H$2:$I$8,2,FALSE) -> #N/A | AX11: =N11 -> 14104.69 | AY11: =P11 -> 5975.54 | AZ11: =Q11 -> 0 | BA11: =R11 -> 0 | BB11: =T11 -> 0 | BC11: =S11+U11 -> 0 | BD11: =SUM(AD11:AF11) -> 0 | BE11: =SUM(AG11:AI11) -> 0 | BF11: =IF($M11="Yes",0,IF(ISNUMBER(SEARCH("LH",F11)),SUM($AM11+$AN11),IF($N11=0,SUM(AF11+AG11+AH11+AM11+AN11),$N11))) -> 0 | BG11: =IF($M11="Yes",0,IF(ISNUMBER(SEARCH("LH",F11)),$AL11,IF(SUM($P11:$S11)=0,SUM(AE11+AI11+AL11),SUM($P11:$S11)))) -> 0 | BH11: =IF(M11="yes",0,IF(ISNUMBER(SEARCH("LH",F11)),AK11,IF(SUM(T11+U11)=0,SUM(AD11+AK11),SUM(T11+U11)))) -> 0 | BI11: =ROUND(SUM($AP11:$AS11),2) -> 0 | BJ11: =SUM(BD11:BH11)+SUM(AO11:AS11)+O11 -> 0 | BK11: =ROUND($AX11/$AB11,2) -> 14104.69 | BL11: =ROUND(SUM($AY11:$BA11)/$AC11+($AX11/$AC11-$BK11),2) -> 5975.54 | BM11: =ROUND($BB11/$AC11,2) -> 0 | BN11: =ROUND($BC11/$AC11,2) -> 0 | BO11: =ROUND($BF11/AB11,2) -> 0 | BP11: =ROUND(IF($BL11=0,0,$BL11+IF($S11=0,0,$BN11)),2) -> 5975.54 | BQ11: =ROUND(IF($BM11=0,0,$BM11+IF($U11=0,0,$BN11)),2) -> 0 | BR11: =ROUND(SUM($AP11:$AS11)/$AC11,2) -> 0 | BS11: =SUM(BO11:BR11) -> 5975.54 | BU11: =SUM(AD11:AG11)+SUM(BF11:BH11) -> 0 | BV11: =SUM(N11:U11) -> 20080.23 | BW11: =SUM(AP11:AS11) -> 0 | BX11: =SUM(AD11,AE11,AF11) -> 0 | BY11: =BU11-BV11 -> -20080.23 | BZ11: =N11+P11+Q11+R11+S11+T11+U11 -> 20080.23 | CA11: Domestic | CB11: =IF(SUM(AD11:AJ11)=0,"Equity","Debt") -> Equity | CC11: =IF(RIGHT(CV11,4)="(GP)","General Partners",IF(RIGHT(CV11,5)="(ALP)","GP Excess",CV11)) -> LP SCH A 3 | CD11: =F11&"_"&AV11 -> SCH A Legal Entity 6_Deal 1 | CE11: =B11&"_"&G11&"_"&E11 -> Deal 1_Partner 3_Partnership 5 | CF11: =IFERROR(VLOOKUP(CE11,[1]Mapping!A:E,5,0),"") | CG11: Deal 1 | CO11: =IF(FM11<>"",FM11,FJ11) -> 0 | CV11: LP SCH A 3 | CX11: Deal 1
A12: 45382 | B12: =IFERROR(VLOOKUP(CG12,CH:CI,2,0),CG12) -> Deal 2 | C12: Tranche 2 | D12: Position 2 | E12: Partnership 3 | F12: SCH A Legal Entity 5 | G12: Partner 6 | H12: =IF(CF12<>"",CF12,CC12) -> LP SCH A 6 | I12: Partner ID 5 | J12: USD | K12: Vehicle 5 | L12: Disposition | N12: 0 | O12: 0 | P12: 719.58 | Q12: 0 | R12: 0 | S12: 0 | T12: 0 | U12: 0 | V12: 0 | W12: 0 | X12: 719.58 | Y12: 0 | Z12: 0 | AA12: 0 | AB12: 1 | AC12: 1 | AD12: 0 | AE12: 0 | AF12: 0 | AG12: 0 | AH12: 0 | AI12: 0 | AJ12: 0 | AK12: 0 | AL12: 719.58 | AM12: 0 | AN12: 0 | AO12: 0 | AP12: 0 | AQ12: 0 | AR12: 0 | AS12: 0 | AT12: =VLOOKUP(H12,Control!B:C,2,0) -> 6 | AV12: =IFERROR(VLOOKUP($B12,'[1]Accounts - MDM Data'!$N$1:$O$5,2,0),$B12) -> Deal 2 | AW12: =VLOOKUP(H12,'[1]Accounts - MDM Data'!$H$2:$I$8,2,FALSE) -> #N/A | AX12: =N12 -> 0 | AY12: =P12 -> 719.58 | AZ12: =Q12 -> 0 | BA12: =R12 -> 0 | BB12: =T12 -> 0 | BC12: =S12+U12 -> 0 | BD12: =SUM(AD12:AF12) -> 0 | BE12: =SUM(AG12:AI12) -> 0 | BF12: =IF($M12="Yes",0,IF(ISNUMBER(SEARCH("LH",F12)),SUM($AM12+$AN12),IF($N12=0,SUM(AF12+AG12+AH12+AM12+AN12),$N12))) -> 0 | BG12: =IF($M12="Yes",0,IF(ISNUMBER(SEARCH("LH",F12)),$AL12,IF(SUM($P12:$S12)=0,SUM(AE12+AI12+AL12),SUM($P12:$S12)))) -> 719.58 | BH12: =IF(M12="yes",0,IF(ISNUMBER(SEARCH("LH",F12)),AK12,IF(SUM(T12+U12)=0,SUM(AD12+AK12),SUM(T12+U12)))) -> 0 | BI12: =ROUND(SUM($AP12:$AS12),2) -> 0 | BJ12: =SUM(BD12:BH12)+SUM(AO12:AS12)+O12 -> 719.58 | BK12: =ROUND($AX12/$AB12,2) -> 0 | BL12: =ROUND(SUM($AY12:$BA12)/$AC12+($AX12/$AC12-$BK12),2) -> 719.58 | BM12: =ROUND($BB12/$AC12,2) -> 0 | BN12: =ROUND($BC12/$AC12,2) -> 0 | BO12: =ROUND($BF12/AB12,2) -> 0 | BP12: =ROUND(IF($BL12=0,0,$BL12+IF($S12=0,0,$BN12)),2) -> 719.58 | BQ12: =ROUND(IF($BM12=0,0,$BM12+IF($U12=0,0,$BN12)),2) -> 0 | BR12: =ROUND(SUM($AP12:$AS12)/$AC12,2) -> 0 | BS12: =SUM(BO12:BR12) -> 719.58 | BU12: =SUM(AD12:AG12)+SUM(BF12:BH12) -> 719.58 | BV12: =SUM(N12:U12) -> 719.58 | BW12: =SUM(AP12:AS12) -> 0 | BX12: =SUM(AD12,AE12,AF12) -> 0 | BY12: =BU12-BV12 -> 0 | BZ12: =N12+P12+Q12+R12+S12+T12+U12 -> 719.58 | CA12: Domestic | CB12: =IF(SUM(AD12:AJ12)=0,"Equity","Debt") -> Equity | CC12: =IF(RIGHT(CV12,4)="(GP)","General Partners",IF(RIGHT(CV12,5)="(ALP)","GP Excess",CV12)) -> LP SCH A 6 | CD12: =F12&"_"&AV12 -> SCH A Legal Entity 5_Deal 2 | CE12: =B12&"_"&G12&"_"&E12 -> Deal 2_Partner 6_Partnership 3 | CF12: =IFERROR(VLOOKUP(CE12,[1]Mapping!A:E,5,0),"") | CG12: Deal 2 | CO12: =IF(FM12<>"",FM12,FJ12) -> 0 | CV12: LP SCH A 6 | CX12: Deal 2
A13: 45382 | B13: =IFERROR(VLOOKUP(CG13,CH:CI,2,0),CG13) -> Deal 2 | C13: Tranche 2 | D13: Position 2 | E13: Partnership 6 | F13: SCH A Legal Entity 7 | G13: Partner 1 | H13: =IF(CF13<>"",CF13,CC13) -> LP SCH A 1 | I13: Partner ID 7 | J13: USD | K13: Vehicle 7 | L13: Disposition | N13: 0 | O13: 0 | P13: 0 | Q13: 0 | R13: 0 | S13: 0 | T13: 0 | U13: 0 | V13: 0 | W13: 0 | X13: 0 | Y13: 0 | Z13: 0 | AA13: 0 | AB13: 1 | AC13: 1 | AD13: 0 | AE13: 0 | AF13: 0 | AG13: 0 | AH13: 0 | AI13: 0 | AJ13: 0 | AK13: 0 | AL13: 452.31 | AM13: 0 | AN13: 0 | AO13: 0 | AP13: 0 | AQ13: 0 | AR13: 0 | AS13: -22.62 | AT13: =VLOOKUP(H13,Control!B:C,2,0) -> 1 | AV13: =IFERROR(VLOOKUP($B13,'[1]Accounts - MDM Data'!$N$1:$O$5,2,0),$B13) -> Deal 2 | AW13: =VLOOKUP(H13,'[1]Accounts - MDM Data'!$H$2:$I$8,2,FALSE) -> #N/A | AX13: =N13 -> 0 | AY13: =P13 -> 0 | AZ13: =Q13 -> 0 | BA13: =R13 -> 0 | BB13: =T13 -> 0 | BC13: =S13+U13 -> 0 | BD13: =SUM(AD13:AF13) -> 0 | BE13: =SUM(AG13:AI13) -> 0 | BF13: =IF($M13="Yes",0,IF(ISNUMBER(SEARCH("LH",F13)),SUM($AM13+$AN13),IF($N13=0,SUM(AF13+AG13+AH13+AM13+AN13),$N13))) -> 0 | BG13: =IF($M13="Yes",0,IF(ISNUMBER(SEARCH("LH",F13)),$AL13,IF(SUM($P13:$S13)=0,SUM(AE13+AI13+AL13),SUM($P13:$S13)))) -> 452.31 | BH13: =IF(M13="yes",0,IF(ISNUMBER(SEARCH("LH",F13)),AK13,IF(SUM(T13+U13)=0,SUM(AD13+AK13),SUM(T13+U13)))) -> 0 | BI13: =ROUND(SUM($AP13:$AS13),2) -> -22.62 | BJ13: =SUM(BD13:BH13)+SUM(AO13:AS13)+O13 -> 429.69 | BK13: =ROUND($AX13/$AB13,2) -> 0 | BL13: =ROUND(SUM($AY13:$BA13)/$AC13+($AX13/$AC13-$BK13),2) -> 0 | BM13: =ROUND($BB13/$AC13,2) -> 0 | BN13: =ROUND($BC13/$AC13,2) -> 0 | BO13: =ROUND($BF13/AB13,2) -> 0 | BP13: =ROUND(IF($BL13=0,0,$BL13+IF($S13=0,0,$BN13)),2) -> 0 | BQ13: =ROUND(IF($BM13=0,0,$BM13+IF($U13=0,0,$BN13)),2) -> 0 | BR13: =ROUND(SUM($AP13:$AS13)/$AC13,2) -> -22.62 | BS13: =SUM(BO13:BR13) -> -22.62 | BU13: =SUM(AD13:AG13)+SUM(BF13:BH13) -> 452.31 | BV13: =SUM(N13:U13) -> 0 | BW13: =SUM(AP13:AS13) -> -22.62 | BX13: =SUM(AD13,AE13,AF13) -> 0 | BY13: =BU13-BV13 -> 452.31 | BZ13: =N13+P13+Q13+R13+S13+T13+U13 -> 0 | CA13: Domestic | CB13: =IF(SUM(AD13:AJ13)=0,"Equity","Debt") -> Equity | CC13: =IF(RIGHT(CV13,4)="(GP)","General Partners",IF(RIGHT(CV13,5)="(ALP)","GP Excess",CV13)) -> LP SCH A 1 | CD13: =F13&"_"&AV13 -> SCH A Legal Entity 7_Deal 2 | CE13: =B13&"_"&G13&"_"&E13 -> Deal 2_Partner 1_Partnership 6 | CF13: =IFERROR(VLOOKUP(CE13,[1]Mapping!A:E,5,0),"") | CG13: Deal 2 | CO13: =IF(FM13<>"",FM13,FJ13) -> 0 | CV13: LP SCH A 1 | CX13: Deal 2
A14: 45382 | B14: =IFERROR(VLOOKUP(CG14,CH:CI,2,0),CG14) -> Deal 2 | C14: Tranche 2 | D14: Position 2 | E14: Partnership 7 | F14: SCH A Legal Entity 8 | G14: Partner 2 | H14: =IF(CF14<>"",CF14,CC14) -> LP SCH A 2 | I14: Partner ID 8 | J14: USD | K14: Vehicle 8 | L14: Disposition | N14: 0 | O14: 0 | P14: 0 | Q14: 0 | R14: 0 | S14: 0 | T14: 0 | U14: 0 | V14: 0 | W14: 0 | X14: 0 | Y14: 0 | Z14: 0 | AA14: 0 | AB14: 1 | AC14: 1 | AD14: 0 | AE14: 0 | AF14: 0 | AG14: 0 | AH14: 0 | AI14: 0 | AJ14: 0 | AK14: 0 | AL14: 10279.69 | AM14: 0 | AN14: 0 | AO14: 0 | AP14: 0 | AQ14: 0 | AR14: -3083.91 | AS14: 0 | AT14: =VLOOKUP(H14,Control!B:C,2,0) -> 2 | AV14: =IFERROR(VLOOKUP($B14,'[1]Accounts - MDM Data'!$N$1:$O$5,2,0),$B14) -> Deal 2 | AW14: =VLOOKUP(H14,'[1]Accounts - MDM Data'!$H$2:$I$8,2,FALSE) -> #N/A | AX14: =N14 -> 0 | AY14: =P14 -> 0 | AZ14: =Q14 -> 0 | BA14: =R14 -> 0 | BB14: =T14 -> 0 | BC14: =S14+U14 -> 0 | BD14: =SUM(AD14:AF14) -> 0 | BE14: =SUM(AG14:AI14) -> 0 | BF14: =IF($M14="Yes",0,IF(ISNUMBER(SEARCH("LH",F14)),SUM($AM14+$AN14),IF($N14=0,SUM(AF14+AG14+AH14+AM14+AN14),$N14))) -> 0 | BG14: =IF($M14="Yes",0,IF(ISNUMBER(SEARCH("LH",F14)),$AL14,IF(SUM($P14:$S14)=0,SUM(AE14+AI14+AL14),SUM($P14:$S14)))) -> 10279.69 | BH14: =IF(M14="yes",0,IF(ISNUMBER(SEARCH("LH",F14)),AK14,IF(SUM(T14+U14)=0,SUM(AD14+AK14),SUM(T14+U14)))) -> 0 | BI14: =ROUND(SUM($AP14:$AS14),2) -> -3083.91 | BJ14: =SUM(BD14:BH14)+SUM(AO14:AS14)+O14 -> 7195.78 | BK14: =ROUND($AX14/$AB14,2) -> 0 | BL14: =ROUND(SUM($AY14:$BA14)/$AC14+($AX14/$AC14-$BK14),2) -> 0 | BM14: =ROUND($BB14/$AC14,2) -> 0 | BN14: =ROUND($BC14/$AC14,2) -> 0 | BO14: =ROUND($BF14/AB14,2) -> 0 | BP14: =ROUND(IF($BL14=0,0,$BL14+IF($S14=0,0,$BN14)),2) -> 0 | BQ14: =ROUND(IF($BM14=0,0,$BM14+IF($U14=0,0,$BN14)),2) -> 0 | BR14: =ROUND(SUM($AP14:$AS14)/$AC14,2) -> -3083.91 | BS14: =SUM(BO14:BR14) -> -3083.91 | BU14: =SUM(AD14:AG14)+SUM(BF14:BH14) -> 10279.69 | BV14: =SUM(N14:U14) -> 0 | BW14: =SUM(AP14:AS14) -> -3083.91 | BX14: =SUM(AD14,AE14,AF14) -> 0 | BY14: =BU14-BV14 -> 10279.69 | BZ14: =N14+P14+Q14+R14+S14+T14+U14 -> 0 | CA14: Domestic | CB14: =IF(SUM(AD14:AJ14)=0,"Equity","Debt") -> Equity | CC14: =IF(RIGHT(CV14,4)="(GP)","General Partners",IF(RIGHT(CV14,5)="(ALP)","GP Excess",CV14)) -> LP SCH A 2 | CD14: =F14&"_"&AV14 -> SCH A Legal Entity 8_Deal 2 | CE14: =B14&"_"&G14&"_"&E14 -> Deal 2_Partner 2_Partnership 7 | CF14: =IFERROR(VLOOKUP(CE14,[1]Mapping!A:E,5,0),"") | CG14: Deal 2 | CO14: =IF(FM14<>"",FM14,FJ14) -> 0 | CV14: LP SCH A 2 | CX14: Deal 2
A15: 45382 | B15: =IFERROR(VLOOKUP(CG15,CH:CI,2,0),CG15) -> Deal 2 | C15: Tranche 2 | D15: Position 2 | E15: Partnership 8 | F15: SCH A Legal Entity 9 | G15: Partner 5 | H15: =IF(CF15<>"",CF15,CC15) -> LP SCH A 5 | I15: Partner ID 9 | J15: USD | K15: Vehicle 9 | L15: Disposition | N15: 0 | O15: 0 | P15: 599.51 | Q15: 0 | R15: 0 | S15: 0 | T15: 0 | U15: 0 | V15: 0 | W15: 0 | X15: 599.51 | Y15: 0 | Z15: 0 | AA15: 0 | AB15: 1 | AC15: 1 | AD15: 0 | AE15: 0 | AF15: 0 | AG15: 0 | AH15: 0 | AI15: 0 | AJ15: 0 | AK15: 0 | AL15: 599.51 | AM15: 0 | AN15: 0 | AO15: 0 | AP15: 0 | AQ15: 0 | AR15: 0 | AS15: 0 | AT15: =VLOOKUP(H15,Control!B:C,2,0) -> 5 | AV15: =IFERROR(VLOOKUP($B15,'[1]Accounts - MDM Data'!$N$1:$O$5,2,0),$B15) -> Deal 2 | AW15: =VLOOKUP(H15,'[1]Accounts - MDM Data'!$H$2:$I$8,2,FALSE) -> #N/A | AX15: =N15 -> 0 | AY15: =P15 -> 599.51 | AZ15: =Q15 -> 0 | BA15: =R15 -> 0 | BB15: =T15 -> 0 | BC15: =S15+U15 -> 0 | BD15: =SUM(AD15:AF15) -> 0 | BE15: =SUM(AG15:AI15) -> 0 | BF15: =IF($M15="Yes",0,IF(ISNUMBER(SEARCH("LH",F15)),SUM($AM15+$AN15),IF($N15=0,SUM(AF15+AG15+AH15+AM15+AN15),$N15))) -> 0 | BG15: =IF($M15="Yes",0,IF(ISNUMBER(SEARCH("LH",F15)),$AL15,IF(SUM($P15:$S15)=0,SUM(AE15+AI15+AL15),SUM($P15:$S15)))) -> 599.51 | BH15: =IF(M15="yes",0,IF(ISNUMBER(SEARCH("LH",F15)),AK15,IF(SUM(T15+U15)=0,SUM(AD15+AK15),SUM(T15+U15)))) -> 0 | BI15: =ROUND(SUM($AP15:$AS15),2) -> 0 | BJ15: =SUM(BD15:BH15)+SUM(AO15:AS15)+O15 -> 599.51 | BK15: =ROUND($AX15/$AB15,2) -> 0 | BL15: =ROUND(SUM($AY15:$BA15)/$AC15+($AX15/$AC15-$BK15),2) -> 599.51 | BM15: =ROUND($BB15/$AC15,2) -> 0 | BN15: =ROUND($BC15/$AC15,2) -> 0 | BO15: =ROUND($BF15/AB15,2) -> 0 | BP15: =ROUND(IF($BL15=0,0,$BL15+IF($S15=0,0,$BN15)),2) -> 599.51 | BQ15: =ROUND(IF($BM15=0,0,$BM15+IF($U15=0,0,$BN15)),2) -> 0 | BR15: =ROUND(SUM($AP15:$AS15)/$AC15,2) -> 0 | BS15: =SUM(BO15:BR15) -> 599.51 | BU15: =SUM(AD15:AG15)+SUM(BF15:BH15) -> 599.51 | BV15: =SUM(N15:U15) -> 599.51 | BW15: =SUM(AP15:AS15) -> 0 | BX15: =SUM(AD15,AE15,AF15) -> 0 | BY15: =BU15-BV15 -> 0 | BZ15: =N15+P15+Q15+R15+S15+T15+U15 -> 599.51 | CA15: Domestic | CB15: =IF(SUM(AD15:AJ15)=0,"Equity","Debt") -> Equity | CC15: =IF(RIGHT(CV15,4)="(GP)","General Partners",IF(RIGHT(CV15,5)="(ALP)","GP Excess",CV15)) -> LP SCH A 5 | CD15: =F15&"_"&AV15 -> SCH A Legal Entity 9_Deal 2 | CE15: =B15&"_"&G15&"_"&E15 -> Deal 2_Partner 5_Partnership 8 | CF15: =IFERROR(VLOOKUP(CE15,[1]Mapping!A:E,5,0),"") | CG15: Deal 2 | CO15: =IF(FM15<>"",FM15,FJ15) -> 0 | CV15: LP SCH A 5 | CX15: Deal 2
A16: 45382 | B16: =IFERROR(VLOOKUP(CG16,CH:CI,2,0),CG16) -> Deal 2 | C16: Tranche 2 | D16: Position 2 | E16: Partnership 9 | F16: SCH A Legal Entity 10 | G16: Partner 7 | H16: =IF(CF16<>"",CF16,CC16) -> LP SCH A 7 | I16: Partner ID 10 | J16: USD | K16: Vehicle 10 | L16: Disposition | N16: 0 | O16: 0 | P16: 308.39 | Q16: 0 | R16: 0 | S16: 0 | T16: 0 | U16: 0 | V16: 0 | W16: 0 | X16: 308.39 | Y16: 0 | Z16: 0 | AA16: 0 | AB16: 1 | AC16: 1 | AD16: 0 | AE16: 0 | AF16: 0 | AG16: 0 | AH16: 0 | AI16: 0 | AJ16: 0 | AK16: 0 | AL16: 308.39 | AM16: 0 | AN16: 0 | AO16: 0 | AP16: 0 | AQ16: 0 | AR16: 0 | AS16: 0 | AT16: =VLOOKUP(H16,Control!B:C,2,0) -> 7 | AV16: =IFERROR(VLOOKUP($B16,'[1]Accounts - MDM Data'!$N$1:$O$5,2,0),$B16) -> Deal 2 | AW16: =VLOOKUP(H16,'[1]Accounts - MDM Data'!$H$2:$I$8,2,FALSE) -> #N/A | AX16: =N16 -> 0 | AY16: =P16 -> 308.39 | AZ16: =Q16 -> 0 | BA16: =R16 -> 0 | BB16: =T16 -> 0 | BC16: =S16+U16 -> 0 | BD16: =SUM(AD16:AF16) -> 0 | BE16: =SUM(AG16:AI16) -> 0 | BF16: =IF($M16="Yes",0,IF(ISNUMBER(SEARCH("LH",F16)),SUM($AM16+$AN16),IF($N16=0,SUM(AF16+AG16+AH16+AM16+AN16),$N16))) -> 0 | BG16: =IF($M16="Yes",0,IF(ISNUMBER(SEARCH("LH",F16)),$AL16,IF(SUM($P16:$S16)=0,SUM(AE16+AI16+AL16),SUM($P16:$S16)))) -> 308.39 | BH16: =IF(M16="yes",0,IF(ISNUMBER(SEARCH("LH",F16)),AK16,IF(SUM(T16+U16)=0,SUM(AD16+AK16),SUM(T16+U16)))) -> 0 | BI16: =ROUND(SUM($AP16:$AS16),2) -> 0 | BJ16: =SUM(BD16:BH16)+SUM(AO16:AS16)+O16 -> 308.39 | BK16: =ROUND($AX16/$AB16,2) -> 0 | BL16: =ROUND(SUM($AY16:$BA16)/$AC16+($AX16/$AC16-$BK16),2) -> 308.39 | BM16: =ROUND($BB16/$AC16,2) -> 0 | BN16: =ROUND($BC16/$AC16,2) -> 0 | BO16: =ROUND($BF16/AB16,2) -> 0 | BP16: =ROUND(IF($BL16=0,0,$BL16+IF($S16=0,0,$BN16)),2) -> 308.39 | BQ16: =ROUND(IF($BM16=0,0,$BM16+IF($U16=0,0,$BN16)),2) -> 0 | BR16: =ROUND(SUM($AP16:$AS16)/$AC16,2) -> 0 | BS16: =SUM(BO16:BR16) -> 308.39 | BU16: =SUM(AD16:AG16)+SUM(BF16:BH16) -> 308.39 | BV16: =SUM(N16:U16) -> 308.39 | BW16: =SUM(AP16:AS16) -> 0 | BX16: =SUM(AD16,AE16,AF16) -> 0 | BY16: =BU16-BV16 -> 0 | BZ16: =N16+P16+Q16+R16+S16+T16+U16 -> 308.39 | CA16: Domestic | CB16: =IF(SUM(AD16:AJ16)=0,"Equity","Debt") -> Equity | CC16: =IF(RIGHT(CV16,4)="(GP)","General Partners",IF(RIGHT(CV16,5)="(ALP)","GP Excess",CV16)) -> LP SCH A 7 | CD16: =F16&"_"&AV16 -> SCH A Legal Entity 10_Deal 2 | CE16: =B16&"_"&G16&"_"&E16 -> Deal 2_Partner 7_Partnership 9 | CF16: =IFERROR(VLOOKUP(CE16,[1]Mapping!A:E,5,0),"") | CG16: Deal 2 | CO16: =IF(FM16<>"",FM16,FJ16) -> 0 | CV16: LP SCH A 7 | CX16: Deal 2
A17: 45382 | B17: =IFERROR(VLOOKUP(CG17,CH:CI,2,0),CG17) -> Deal 2 | C17: Tranche 2 | D17: Position 2 | E17: Partnership 10 | F17: SCH A Legal Entity 3 | G17: Partner 3 | H17: =IF(CF17<>"",CF17,CC17) -> LP SCH A 3 | I17: Partner ID 3 | J17: USD | K17: Vehicle 3 | L17: Disposition | N17: 0 | O17: 0 | P17: 0 | Q17: 0 | R17: 0 | S17: 0 | T17: 0 | U17: 0 | V17: 0 | W17: 0 | X17: 0 | Y17: 0 | Z17: 0 | AA17: 0 | AB17: 1 | AC17: 1 | AD17: 0 | AE17: 0 | AF17: 0 | AG17: 0 | AH17: 0 | AI17: 0 | AJ17: 0 | AK17: 0 | AL17: 3527.99 | AM17: 0 | AN17: 0 | AO17: 0 | AP17: 0 | AQ17: 0 | AR17: -1058.4 | AS17: 0 | AT17: =VLOOKUP(H17,Control!B:C,2,0) -> 3 | AV17: =IFERROR(VLOOKUP($B17,'[1]Accounts - MDM Data'!$N$1:$O$5,2,0),$B17) -> Deal 2 | AW17: =VLOOKUP(H17,'[1]Accounts - MDM Data'!$H$2:$I$8,2,FALSE) -> #N/A | AX17: =N17 -> 0 | AY17: =P17 -> 0 | AZ17: =Q17 -> 0 | BA17: =R17 -> 0 | BB17: =T17 -> 0 | BC17: =S17+U17 -> 0 | BD17: =SUM(AD17:AF17) -> 0 | BE17: =SUM(AG17:AI17) -> 0 | BF17: =IF($M17="Yes",0,IF(ISNUMBER(SEARCH("LH",F17)),SUM($AM17+$AN17),IF($N17=0,SUM(AF17+AG17+AH17+AM17+AN17),$N17))) -> 0 | BG17: =IF($M17="Yes",0,IF(ISNUMBER(SEARCH("LH",F17)),$AL17,IF(SUM($P17:$S17)=0,SUM(AE17+AI17+AL17),SUM($P17:$S17)))) -> 3527.99 | BH17: =IF(M17="yes",0,IF(ISNUMBER(SEARCH("LH",F17)),AK17,IF(SUM(T17+U17)=0,SUM(AD17+AK17),SUM(T17+U17)))) -> 0 | BI17: =ROUND(SUM($AP17:$AS17),2) -> -1058.4 | BJ17: =SUM(BD17:BH17)+SUM(AO17:AS17)+O17 -> 2469.59 | BK17: =ROUND($AX17/$AB17,2) -> 0 | BL17: =ROUND(SUM($AY17:$BA17)/$AC17+($AX17/$AC17-$BK17),2) -> 0 | BM17: =ROUND($BB17/$AC17,2) -> 0 | BN17: =ROUND($BC17/$AC17,2) -> 0 | BO17: =ROUND($BF17/AB17,2) -> 0 | BP17: =ROUND(IF($BL17=0,0,$BL17+IF($S17=0,0,$BN17)),2) -> 0 | BQ17: =ROUND(IF($BM17=0,0,$BM17+IF($U17=0,0,$BN17)),2) -> 0 | BR17: =ROUND(SUM($AP17:$AS17)/$AC17,2) -> -1058.4 | BS17: =SUM(BO17:BR17) -> -1058.4 | BU17: =SUM(AD17:AG17)+SUM(BF17:BH17) -> 3527.99 | BV17: =SUM(N17:U17) -> 0 | BW17: =SUM(AP17:AS17) -> -1058.4 | BX17: =SUM(AD17,AE17,AF17) -> 0 | BY17: =BU17-BV17 -> 3527.99 | BZ17: =N17+P17+Q17+R17+S17+T17+U17 -> 0 | CA17: Domestic | CB17: =IF(SUM(AD17:AJ17)=0,"Equity","Debt") -> Equity | CC17: =IF(RIGHT(CV17,4)="(GP)","General Partners",IF(RIGHT(CV17,5)="(ALP)","GP Excess",CV17)) -> LP SCH A 3 | CD17: =F17&"_"&AV17 -> SCH A Legal Entity 3_Deal 2 | CE17: =B17&"_"&G17&"_"&E17 -> Deal 2_Partner 3_Partnership 10 | CF17: =IFERROR(VLOOKUP(CE17,[1]Mapping!A:E,5,0),"") | CG17: Deal 2 | CO17: =IF(FM17<>"",FM17,FJ17) -> 0 | CV17: LP SCH A 3 | CX17: Deal 2
A18: 45382 | B18: =IFERROR(VLOOKUP(CG18,CH:CI,2,0),CG18) -> Deal 2 | C18: Tranche 2 | D18: Position 2 | E18: Partnership 11 | F18: SCH A Legal Entity 11 | G18: Partner 4 | H18: =IF(CF18<>"",CF18,CC18) -> LP SCH A 4 | I18: Partner ID 11 | J18: USD | K18: Vehicle 11 | L18: Disposition | N18: 0 | O18: 0 | P18: 4111.88 | Q18: 0 | R18: 0 | S18: 0 | T18: 0 | U18: 0 | V18: 0 | W18: 0 | X18: 4111.88 | Y18: 0 | Z18: 0 | AA18: 0 | AB18: 1 | AC18: 1 | AD18: 0 | AE18: 0 | AF18: 0 | AG18: 0 | AH18: 0 | AI18: 0 | AJ18: 0 | AK18: 0 | AL18: 4111.88 | AM18: 0 | AN18: 0 | AO18: 0 | AP18: 0 | AQ18: 0 | AR18: 0 | AS18: 0 | AT18: =VLOOKUP(H18,Control!B:C,2,0) -> 4 | AV18: =IFERROR(VLOOKUP($B18,'[1]Accounts - MDM Data'!$N$1:$O$5,2,0),$B18) -> Deal 2 | AW18: =VLOOKUP(H18,'[1]Accounts - MDM Data'!$H$2:$I$8,2,FALSE) -> #N/A | AX18: =N18 -> 0 | AY18: =P18 -> 4111.88 | AZ18: =Q18 -> 0 | BA18: =R18 -> 0 | BB18: =T18 -> 0 | BC18: =S18+U18 -> 0 | BD18: =SUM(AD18:AF18) -> 0 | BE18: =SUM(AG18:AI18) -> 0 | BF18: =IF($M18="Yes",0,IF(ISNUMBER(SEARCH("LH",F18)),SUM($AM18+$AN18),IF($N18=0,SUM(AF18+AG18+AH18+AM18+AN18),$N18))) -> 0 | BG18: =IF($M18="Yes",0,IF(ISNUMBER(SEARCH("LH",F18)),$AL18,IF(SUM($P18:$S18)=0,SUM(AE18+AI18+AL18),SUM($P18:$S18)))) -> 4111.88 | BH18: =IF(M18="yes",0,IF(ISNUMBER(SEARCH("LH",F18)),AK18,IF(SUM(T18+U18)=0,SUM(AD18+AK18),SUM(T18+U18)))) -> 0 | BI18: =ROUND(SUM($AP18:$AS18),2) -> 0 | BJ18: =SUM(BD18:BH18)+SUM(AO18:AS18)+O18 -> 4111.88 | BK18: =ROUND($AX18/$AB18,2) -> 0 | BL18: =ROUND(SUM($AY18:$BA18)/$AC18+($AX18/$AC18-$BK18),2) -> 4111.88 | BM18: =ROUND($BB18/$AC18,2) -> 0 | BN18: =ROUND($BC18/$AC18,2) -> 0 | BO18: =ROUND($BF18/AB18,2) -> 0 | BP18: =ROUND(IF($BL18=0,0,$BL18+IF($S18=0,0,$BN18)),2) -> 4111.88 | BQ18: =ROUND(IF($BM18=0,0,$BM18+IF($U18=0,0,$BN18)),2) -> 0 | BR18: =ROUND(SUM($AP18:$AS18)/$AC18,2) -> 0 | BS18: =SUM(BO18:BR18) -> 4111.88 | BU18: =SUM(AD18:AG18)+SUM(BF18:BH18) -> 4111.88 | BV18: =SUM(N18:U18) -> 4111.88 | BW18: =SUM(AP18:AS18) -> 0 | BX18: =SUM(AD18,AE18,AF18) -> 0 | BY18: =BU18-BV18 -> 0 | BZ18: =N18+P18+Q18+R18+S18+T18+U18 -> 4111.88 | CA18: Domestic | CB18: =IF(SUM(AD18:AJ18)=0,"Equity","Debt") -> Equity | CC18: =IF(RIGHT(CV18,4)="(GP)","General Partners",IF(RIGHT(CV18,5)="(ALP)","GP Excess",CV18)) -> LP SCH A 4 | CD18: =F18&"_"&AV18 -> SCH A Legal Entity 11_Deal 2 | CE18: =B18&"_"&G18&"_"&E18 -> Deal 2_Partner 4_Partnership 11 | CF18: =IFERROR(VLOOKUP(CE18,[1]Mapping!A:E,5,0),"") | CG18: Deal 2 | CO18: =IF(FM18<>"",FM18,FJ18) -> 0 | CV18: LP SCH A 4 | CX18: Deal 2
A19: 45382 | B19: =IFERROR(VLOOKUP(CG19,CH:CI,2,0),CG19) -> Deal 2 | C19: Tranche 2 | D19: Position 2 | E19: Partnership 4 | F19: SCH A Legal Entity 12 | G19: Partner 1 | H19: =IF(CF19<>"",CF19,CC19) -> LP SCH A 1 | I19: Partner ID 12 | J19: USD | K19: Vehicle 12 | L19: Disposition | M19: Yes | N19: 0 | O19: 0 | P19: 452.31 | Q19: 0 | R19: 0 | S19: 0 | T19: 0 | U19: 0 | V19: 0 | W19: 0 | X19: 452.31 | Y19: 0 | Z19: 0 | AA19: 0 | AB19: 1 | AC19: 1 | AD19: 0 | AE19: 0 | AF19: 0 | AG19: 0 | AH19: 0 | AI19: 0 | AJ19: 0 | AK19: 0 | AL19: 0 | AM19: 0 | AN19: 0 | AO19: 0 | AP19: 0 | AQ19: 0 | AR19: 0 | AS19: 0 | AT19: =VLOOKUP(H19,Control!B:C,2,0) -> 1 | AV19: =IFERROR(VLOOKUP($B19,'[1]Accounts - MDM Data'!$N$1:$O$5,2,0),$B19) -> Deal 2 | AW19: =VLOOKUP(H19,'[1]Accounts - MDM Data'!$H$2:$I$8,2,FALSE) -> #N/A | AX19: =N19 -> 0 | AY19: =P19 -> 452.31 | AZ19: =Q19 -> 0 | BA19: =R19 -> 0 | BB19: =T19 -> 0 | BC19: =S19+U19 -> 0 | BD19: =SUM(AD19:AF19) -> 0 | BE19: =SUM(AG19:AI19) -> 0 | BF19: =IF($M19="Yes",0,IF(ISNUMBER(SEARCH("LH",F19)),SUM($AM19+$AN19),IF($N19=0,SUM(AF19+AG19+AH19+AM19+AN19),$N19))) -> 0 | BG19: =IF($M19="Yes",0,IF(ISNUMBER(SEARCH("LH",F19)),$AL19,IF(SUM($P19:$S19)=0,SUM(AE19+AI19+AL19),SUM($P19:$S19)))) -> 0 | BH19: =IF(M19="yes",0,IF(ISNUMBER(SEARCH("LH",F19)),AK19,IF(SUM(T19+U19)=0,SUM(AD19+AK19),SUM(T19+U19)))) -> 0 | BI19: =ROUND(SUM($AP19:$AS19),2) -> 0 | BJ19: =SUM(BD19:BH19)+SUM(AO19:AS19)+O19 -> 0 | BK19: =ROUND($AX19/$AB19,2) -> 0 | BL19: =ROUND(SUM($AY19:$BA19)/$AC19+($AX19/$AC19-$BK19),2) -> 452.31 | BM19: =ROUND($BB19/$AC19,2) -> 0 | BN19: =ROUND($BC19/$AC19,2) -> 0 | BO19: =ROUND($BF19/AB19,2) -> 0 | BP19: =ROUND(IF($BL19=0,0,$BL19+IF($S19=0,0,$BN19)),2) -> 452.31 | BQ19: =ROUND(IF($BM19=0,0,$BM19+IF($U19=0,0,$BN19)),2) -> 0 | BR19: =ROUND(SUM($AP19:$AS19)/$AC19,2) -> 0 | BS19: =SUM(BO19:BR19) -> 452.31 | BU19: =SUM(AD19:AG19)+SUM(BF19:BH19) -> 0 | BV19: =SUM(N19:U19) -> 452.31 | BW19: =SUM(AP19:AS19) -> 0 | BX19: =SUM(AD19,AE19,AF19) -> 0 | BY19: =BU19-BV19 -> -452.31 | BZ19: =N19+P19+Q19+R19+S19+T19+U19 -> 452.31 | CA19: Domestic | CB19: =IF(SUM(AD19:AJ19)=0,"Equity","Debt") -> Equity | CC19: =IF(RIGHT(CV19,4)="(GP)","General Partners",IF(RIGHT(CV19,5)="(ALP)","GP Excess",CV19)) -> LP SCH A 1 | CD19: =F19&"_"&AV19 -> SCH A Legal Entity 12_Deal 2 | CE19: =B19&"_"&G19&"_"&E19 -> Deal 2_Partner 1_Partnership 4 | CF19: =IFERROR(VLOOKUP(CE19,[1]Mapping!A:E,5,0),"") | CG19: Deal 2 | CO19: =IF(FM19<>"",FM19,FJ19) -> 0 | CV19: LP SCH A 1 | CX19: Deal 2
A20: 45382 | B20: =IFERROR(VLOOKUP(CG20,CH:CI,2,0),CG20) -> Deal 2 | C20: Tranche 2 | D20: Position 2 | E20: Partnership 5 | F20: SCH A Legal Entity 12 | G20: Partner 3 | H20: =IF(CF20<>"",CF20,CC20) -> LP SCH A 3 | I20: Partner ID 12 | J20: USD | K20: Vehicle 12 | L20: Disposition | M20: Yes | N20: 0 | O20: 0 | P20: 3527.99 | Q20: 0 | R20: 0 | S20: 0 | T20: 0 | U20: 0 | V20: 0 | W20: 0 | X20: 3527.99 | Y20: 0 | Z20: 0 | AA20: 0 | AB20: 1 | AC20: 1 | AD20: 0 | AE20: 0 | AF20: 0 | AG20: 0 | AH20: 0 | AI20: 0 | AJ20: 0 | AK20: 0 | AL20: 0 | AM20: 0 | AN20: 0 | AO20: 0 | AP20: 0 | AQ20: 0 | AR20: 0 | AS20: 0 | AT20: =VLOOKUP(H20,Control!B:C,2,0) -> 3 | AV20: =IFERROR(VLOOKUP($B20,'[1]Accounts - MDM Data'!$N$1:$O$5,2,0),$B20) -> Deal 2 | AW20: =VLOOKUP(H20,'[1]Accounts - MDM Data'!$H$2:$I$8,2,FALSE) -> #N/A | AX20: =N20 -> 0 | AY20: =P20 -> 3527.99 | AZ20: =Q20 -> 0 | BA20: =R20 -> 0 | BB20: =T20 -> 0 | BC20: =S20+U20 -> 0 | BD20: =SUM(AD20:AF20) -> 0 | BE20: =SUM(AG20:AI20) -> 0 | BF20: =IF($M20="Yes",0,IF(ISNUMBER(SEARCH("LH",F20)),SUM($AM20+$AN20),IF($N20=0,SUM(AF20+AG20+AH20+AM20+AN20),$N20))) -> 0 | BG20: =IF($M20="Yes",0,IF(ISNUMBER(SEARCH("LH",F20)),$AL20,IF(SUM($P20:$S20)=0,SUM(AE20+AI20+AL20),SUM($P20:$S20)))) -> 0 | BH20: =IF(M20="yes",0,IF(ISNUMBER(SEARCH("LH",F20)),AK20,IF(SUM(T20+U20)=0,SUM(AD20+AK20),SUM(T20+U20)))) -> 0 | BI20: =ROUND(SUM($AP20:$AS20),2) -> 0 | BJ20: =SUM(BD20:BH20)+SUM(AO20:AS20)+O20 -> 0 | BK20: =ROUND($AX20/$AB20,2) -> 0 | BL20: =ROUND(SUM($AY20:$BA20)/$AC20+($AX20/$AC20-$BK20),2) -> 3527.99 | BM20: =ROUND($BB20/$AC20,2) -> 0 | BN20: =ROUND($BC20/$AC20,2) -> 0 | BO20: =ROUND($BF20/AB20,2) -> 0 | BP20: =ROUND(IF($BL20=0,0,$BL20+IF($S20=0,0,$BN20)),2) -> 3527.99 | BQ20: =ROUND(IF($BM20=0,0,$BM20+IF($U20=0,0,$BN20)),2) -> 0 | BR20: =ROUND(SUM($AP20:$AS20)/$AC20,2) -> 0 | BS20: =SUM(BO20:BR20) -> 3527.99 | BU20: =SUM(AD20:AG20)+SUM(BF20:BH20) -> 0 | BV20: =SUM(N20:U20) -> 3527.99 | BW20: =SUM(AP20:AS20) -> 0 | BX20: =SUM(AD20,AE20,AF20) -> 0 | BY20: =BU20-BV20 -> -3527.99 | BZ20: =N20+P20+Q20+R20+S20+T20+U20 -> 3527.99 | CA20: Domestic | CB20: =IF(SUM(AD20:AJ20)=0,"Equity","Debt") -> Equity | CC20: =IF(RIGHT(CV20,4)="(GP)","General Partners",IF(RIGHT(CV20,5)="(ALP)","GP Excess",CV20)) -> LP SCH A 3 | CD20: =F20&"_"&AV20 -> SCH A Legal Entity 12_Deal 2 | CE20: =B20&"_"&G20&"_"&E20 -> Deal 2_Partner 3_Partnership 5 | CF20: =IFERROR(VLOOKUP(CE20,[1]Mapping!A:E,5,0),"") | CG20: Deal 2 | CO20: =IF(FM20<>"",FM20,FJ20) -> 0 | CV20: LP SCH A 3 | CX20: Deal 2
A21: 45382 | B21: =IFERROR(VLOOKUP(CG21,CH:CI,2,0),CG21) -> Deal 2 | C21: Tranche 2 | D21: Position 2 | E21: Partnership 4 | F21: SCH A Legal Entity 12 | G21: Partner 2 | H21: =IF(CF21<>"",CF21,CC21) -> LP SCH A 2 | I21: Partner ID 12 | J21: USD | K21: Vehicle 12 | L21: Disposition | M21: Yes | N21: 0 | O21: 0 | P21: 10279.69 | Q21: 0 | R21: 0 | S21: 0 | T21: 0 | U21: 0 | V21: 0 | W21: 0 | X21: 10279.69 | Y21: 0 | Z21: 0 | AA21: 0 | AB21: 1 | AC21: 1 | AD21: 0 | AE21: 0 | AF21: 0 | AG21: 0 | AH21: 0 | AI21: 0 | AJ21: 0 | AK21: 0 | AL21: 0 | AM21: 0 | AN21: 0 | AO21: 0 | AP21: 0 | AQ21: 0 | AR21: 0 | AS21: 0 | AT21: =VLOOKUP(H21,Control!B:C,2,0) -> 2 | AV21: =IFERROR(VLOOKUP($B21,'[1]Accounts - MDM Data'!$N$1:$O$5,2,0),$B21) -> Deal 2 | AW21: =VLOOKUP(H21,'[1]Accounts - MDM Data'!$H$2:$I$8,2,FALSE) -> #N/A | AX21: =N21 -> 0 | AY21: =P21 -> 10279.69 | AZ21: =Q21 -> 0 | BA21: =R21 -> 0 | BB21: =T21 -> 0 | BC21: =S21+U21 -> 0 | BD21: =SUM(AD21:AF21) -> 0 | BE21: =SUM(AG21:AI21) -> 0 | BF21: =IF($M21="Yes",0,IF(ISNUMBER(SEARCH("LH",F21)),SUM($AM21+$AN21),IF($N21=0,SUM(AF21+AG21+AH21+AM21+AN21),$N21))) -> 0 | BG21: =IF($M21="Yes",0,IF(ISNUMBER(SEARCH("LH",F21)),$AL21,IF(SUM($P21:$S21)=0,SUM(AE21+AI21+AL21),SUM($P21:$S21)))) -> 0 | BH21: =IF(M21="yes",0,IF(ISNUMBER(SEARCH("LH",F21)),AK21,IF(SUM(T21+U21)=0,SUM(AD21+AK21),SUM(T21+U21)))) -> 0 | BI21: =ROUND(SUM($AP21:$AS21),2) -> 0 | BJ21: =SUM(BD21:BH21)+SUM(AO21:AS21)+O21 -> 0 | BK21: =ROUND($AX21/$AB21,2) -> 0 | BL21: =ROUND(SUM($AY21:$BA21)/$AC21+($AX21/$AC21-$BK21),2) -> 10279.69 | BM21: =ROUND($BB21/$AC21,2) -> 0 | BN21: =ROUND($BC21/$AC21,2) -> 0 | BO21: =ROUND($BF21/AB21,2) -> 0 | BP21: =ROUND(IF($BL21=0,0,$BL21+IF($S21=0,0,$BN21)),2) -> 10279.69 | BQ21: =ROUND(IF($BM21=0,0,$BM21+IF($U21=0,0,$BN21)),2) -> 0 | BR21: =ROUND(SUM($AP21:$AS21)/$AC21,2) -> 0 | BS21: =SUM(BO21:BR21) -> 10279.69 | BU21: =SUM(AD21:AG21)+SUM(BF21:BH21) -> 0 | BV21: =SUM(N21:U21) -> 10279.69 | BW21: =SUM(AP21:AS21) -> 0 | BX21: =SUM(AD21,AE21,AF21) -> 0 | BY21: =BU21-BV21 -> -10279.69 | BZ21: =N21+P21+Q21+R21+S21+T21+U21 -> 10279.69 | CA21: Domestic | CB21: =IF(SUM(AD21:AJ21)=0,"Equity","Debt") -> Equity | CC21: =IF(RIGHT(CV21,4)="(GP)","General Partners",IF(RIGHT(CV21,5)="(ALP)","GP Excess",CV21)) -> LP SCH A 2 | CD21: =F21&"_"&AV21 -> SCH A Legal Entity 12_Deal 2 | CE21: =B21&"_"&G21&"_"&E21 -> Deal 2_Partner 2_Partnership 4 | CF21: =IFERROR(VLOOKUP(CE21,[1]Mapping!A:E,5,0),"") | CG21: Deal 2 | CO21: =IF(FM21<>"",FM21,FJ21) -> 0 | CV21: LP SCH A 2 | CX21: Deal 2
A22: 45382 | B22: =IFERROR(VLOOKUP(CG22,CH:CI,2,0),CG22) -> Deal 3 | C22: Tranche 3 | D22: Position 3 | E22: Partnership 11 | F22: SCH A Legal Entity 11 | G22: Partner 4 | H22: =IF(CF22<>"",CF22,CC22) -> LP SCH A 4 | I22: Partner ID 11 | J22: USD | K22: Vehicle 11 | L22: Income | N22: 0 | O22: 0 | P22: 0 | Q22: 0 | R22: 0 | S22: 0 | T22: 926.51 | U22: 0 | V22: 0 | W22: 0 | X22: 0 | Y22: 0 | Z22: 926.51 | AA22: 0 | AB22: 1 | AC22: 1 | AD22: 0 | AE22: 0 | AF22: 0 | AG22: 0 | AH22: 0 | AI22: 0 | AJ22: 0 | AK22: 926.51 | AL22: 0 | AM22: 0 | AN22: 0 | AO22: 0 | AP22: 0 | AQ22: 0 | AR22: 0 | AS22: 0 | AT22: =VLOOKUP(H22,Control!B:C,2,0) -> 4 | AV22: =IFERROR(VLOOKUP($B22,'[1]Accounts - MDM Data'!$N$1:$O$5,2,0),$B22) -> Deal 3 | AW22: =VLOOKUP(H22,'[1]Accounts - MDM Data'!$H$2:$I$8,2,FALSE) -> #N/A | AX22: =N22 -> 0 | AY22: =P22 -> 0 | AZ22: =Q22 -> 0 | BA22: =R22 -> 0 | BB22: =T22 -> 926.51 | BC22: =S22+U22 -> 0 | BD22: =SUM(AD22:AF22) -> 0 | BE22: =SUM(AG22:AI22) -> 0 | BF22: =IF($M22="Yes",0,IF(ISNUMBER(SEARCH("LH",F22)),SUM($AM22+$AN22),IF($N22=0,SUM(AF22+AG22+AH22+AM22+AN22),$N22))) -> 0 | BG22: =IF($M22="Yes",0,IF(ISNUMBER(SEARCH("LH",F22)),$AL22,IF(SUM($P22:$S22)=0,SUM(AE22+AI22+AL22),SUM($P22:$S22)))) -> 0 | BH22: =IF(M22="yes",0,IF(ISNUMBER(SEARCH("LH",F22)),AK22,IF(SUM(T22+U22)=0,SUM(AD22+AK22),SUM(T22+U22)))) -> 926.51 | BI22: =ROUND(SUM($AP22:$AS22),2) -> 0 | BJ22: =SUM(BD22:BH22)+SUM(AO22:AS22)+O22 -> 926.51 | BK22: =ROUND($AX22/$AB22,2) -> 0 | BL22: =ROUND(SUM($AY22:$BA22)/$AC22+($AX22/$AC22-$BK22),2) -> 0 | BM22: =ROUND($BB22/$AC22,2) -> 926.51 | BN22: =ROUND($BC22/$AC22,2) -> 0 | BO22: =ROUND($BF22/AB22,2) -> 0 | BP22: =ROUND(IF($BL22=0,0,$BL22+IF($S22=0,0,$BN22)),2) -> 0 | BQ22: =ROUND(IF($BM22=0,0,$BM22+IF($U22=0,0,$BN22)),2) -> 926.51 | BR22: =ROUND(SUM($AP22:$AS22)/$AC22,2) -> 0 | BS22: =SUM(BO22:BR22) -> 926.51 | BU22: =SUM(AD22:AG22)+SUM(BF22:BH22) -> 926.51 | BV22: =SUM(N22:U22) -> 926.51 | BW22: =SUM(AP22:AS22) -> 0 | BX22: =SUM(AD22,AE22,AF22) -> 0 | BY22: =BU22-BV22 -> 0 | BZ22: =N22+P22+Q22+R22+S22+T22+U22 -> 926.51 | CA22: Domestic | CB22: =IF(SUM(AD22:AJ22)=0,"Equity","Debt") -> Equity | CC22: =IF(RIGHT(CV22,4)="(GP)","General Partners",IF(RIGHT(CV22,5)="(ALP)","GP Excess",CV22)) -> LP SCH A 4 | CD22: =F22&"_"&AV22 -> SCH A Legal Entity 11_Deal 3 | CE22: =B22&"_"&G22&"_"&E22 -> Deal 3_Partner 4_Partnership 11 | CF22: =IFERROR(VLOOKUP(CE22,[1]Mapping!A:E,5,0),"") | CG22: Deal 3 | CO22: =IF(FM22<>"",FM22,FJ22) -> 0 | CV22: LP SCH A 4 | CX22: Deal 3
A23: 45382 | B23: =IFERROR(VLOOKUP(CG23,CH:CI,2,0),CG23) -> Deal 3 | C23: Tranche 3 | D23: Position 3 | E23: Partnership 3 | F23: SCH A Legal Entity 5 | G23: Partner 6 | H23: =IF(CF23<>"",CF23,CC23) -> LP SCH A 6 | I23: Partner ID 5 | J23: USD | K23: Vehicle 5 | L23: Income | N23: 0 | O23: 0 | P23: 0 | Q23: 0 | R23: 0 | S23: 0 | T23: 162.14 | U23: 0 | V23: 0 | W23: 0 | X23: 0 | Y23: 0 | Z23: 162.14 | AA23: 0 | AB23: 1 | AC23: 1 | AD23: 0 | AE23: 0 | AF23: 0 | AG23: 0 | AH23: 0 | AI23: 0 | AJ23: 0 | AK23: 162.14 | AL23: 0 | AM23: 0 | AN23: 0 | AO23: 0 | AP23: 0 | AQ23: 0 | AR23: 0 | AS23: 0 | AT23: =VLOOKUP(H23,Control!B:C,2,0) -> 6 | AV23: =IFERROR(VLOOKUP($B23,'[1]Accounts - MDM Data'!$N$1:$O$5,2,0),$B23) -> Deal 3 | AW23: =VLOOKUP(H23,'[1]Accounts - MDM Data'!$H$2:$I$8,2,FALSE) -> #N/A | AX23: =N23 -> 0 | AY23: =P23 -> 0 | AZ23: =Q23 -> 0 | BA23: =R23 -> 0 | BB23: =T23 -> 162.14 | BC23: =S23+U23 -> 0 | BD23: =SUM(AD23:AF23) -> 0 | BE23: =SUM(AG23:AI23) -> 0 | BF23: =IF($M23="Yes",0,IF(ISNUMBER(SEARCH("LH",F23)),SUM($AM23+$AN23),IF($N23=0,SUM(AF23+AG23+AH23+AM23+AN23),$N23))) -> 0 | BG23: =IF($M23="Yes",0,IF(ISNUMBER(SEARCH("LH",F23)),$AL23,IF(SUM($P23:$S23)=0,SUM(AE23+AI23+AL23),SUM($P23:$S23)))) -> 0 | BH23: =IF(M23="yes",0,IF(ISNUMBER(SEARCH("LH",F23)),AK23,IF(SUM(T23+U23)=0,SUM(AD23+AK23),SUM(T23+U23)))) -> 162.14 | BI23: =ROUND(SUM($AP23:$AS23),2) -> 0 | BJ23: =SUM(BD23:BH23)+SUM(AO23:AS23)+O23 -> 162.14 | BK23: =ROUND($AX23/$AB23,2) -> 0 | BL23: =ROUND(SUM($AY23:$BA23)/$AC23+($AX23/$AC23-$BK23),2) -> 0 | BM23: =ROUND($BB23/$AC23,2) -> 162.14 | BN23: =ROUND($BC23/$AC23,2) -> 0 | BO23: =ROUND($BF23/AB23,2) -> 0 | BP23: =ROUND(IF($BL23=0,0,$BL23+IF($S23=0,0,$BN23)),2) -> 0 | BQ23: =ROUND(IF($BM23=0,0,$BM23+IF($U23=0,0,$BN23)),2) -> 162.14 | BR23: =ROUND(SUM($AP23:$AS23)/$AC23,2) -> 0 | BS23: =SUM(BO23:BR23) -> 162.14 | BU23: =SUM(AD23:AG23)+SUM(BF23:BH23) -> 162.14 | BV23: =SUM(N23:U23) -> 162.14 | BW23: =SUM(AP23:AS23) -> 0 | BX23: =SUM(AD23,AE23,AF23) -> 0 | BY23: =BU23-BV23 -> 0 | BZ23: =N23+P23+Q23+R23+S23+T23+U23 -> 162.14 | CA23: Domestic | CB23: =IF(SUM(AD23:AJ23)=0,"Equity","Debt") -> Equity | CC23: =IF(RIGHT(CV23,4)="(GP)","General Partners",IF(RIGHT(CV23,5)="(ALP)","GP Excess",CV23)) -> LP SCH A 6 | CD23: =F23&"_"&AV23 -> SCH A Legal Entity 5_Deal 3 | CE23: =B23&"_"&G23&"_"&E23 -> Deal 3_Partner 6_Partnership 3 | CF23: =IFERROR(VLOOKUP(CE23,[1]Mapping!A:E,5,0),"") | CG23: Deal 3 | CO23: =IF(FM23<>"",FM23,FJ23) -> 0 | CV23: LP SCH A 6 | CX23: Deal 3
A24: 45382 | B24: =IFERROR(VLOOKUP(CG24,CH:CI,2,0),CG24) -> Deal 3 | C24: Tranche 3 | D24: Position 3 | E24: Partnership 8 | F24: SCH A Legal Entity 9 | G24: Partner 5 | H24: =IF(CF24<>"",CF24,CC24) -> LP SCH A 5 | I24: Partner ID 9 | J24: USD | K24: Vehicle 9 | L24: Income | N24: 0 | O24: 0 | P24: 0 | Q24: 0 | R24: 0 | S24: 0 | T24: 135.09 | U24: 0 | V24: 0 | W24: 0 | X24: 0 | Y24: 0 | Z24: 135.09 | AA24: 0 | AB24: 1 | AC24: 1 | AD24: 0 | AE24: 0 | AF24: 0 | AG24: 0 | AH24: 0 | AI24: 0 | AJ24: 0 | AK24: 135.09 | AL24: 0 | AM24: 0 | AN24: 0 | AO24: 0 | AP24: 0 | AQ24: 0 | AR24: 0 | AS24: 0 | AT24: =VLOOKUP(H24,Control!B:C,2,0) -> 5 | AV24: =IFERROR(VLOOKUP($B24,'[1]Accounts - MDM Data'!$N$1:$O$5,2,0),$B24) -> Deal 3 | AW24: =VLOOKUP(H24,'[1]Accounts - MDM Data'!$H$2:$I$8,2,FALSE) -> #N/A | AX24: =N24 -> 0 | AY24: =P24 -> 0 | AZ24: =Q24 -> 0 | BA24: =R24 -> 0 | BB24: =T24 -> 135.09 | BC24: =S24+U24 -> 0 | BD24: =SUM(AD24:AF24) -> 0 | BE24: =SUM(AG24:AI24) -> 0 | BF24: =IF($M24="Yes",0,IF(ISNUMBER(SEARCH("LH",F24)),SUM($AM24+$AN24),IF($N24=0,SUM(AF24+AG24+AH24+AM24+AN24),$N24))) -> 0 | BG24: =IF($M24="Yes",0,IF(ISNUMBER(SEARCH("LH",F24)),$AL24,IF(SUM($P24:$S24)=0,SUM(AE24+AI24+AL24),SUM($P24:$S24)))) -> 0 | BH24: =IF(M24="yes",0,IF(ISNUMBER(SEARCH("LH",F24)),AK24,IF(SUM(T24+U24)=0,SUM(AD24+AK24),SUM(T24+U24)))) -> 135.09 | BI24: =ROUND(SUM($AP24:$AS24),2) -> 0 | BJ24: =SUM(BD24:BH24)+SUM(AO24:AS24)+O24 -> 135.09 | BK24: =ROUND($AX24/$AB24,2) -> 0 | BL24: =ROUND(SUM($AY24:$BA24)/$AC24+($AX24/$AC24-$BK24),2) -> 0 | BM24: =ROUND($BB24/$AC24,2) -> 135.09 | BN24: =ROUND($BC24/$AC24,2) -> 0 | BO24: =ROUND($BF24/AB24,2) -> 0 | BP24: =ROUND(IF($BL24=0,0,$BL24+IF($S24=0,0,$BN24)),2) -> 0 | BQ24: =ROUND(IF($BM24=0,0,$BM24+IF($U24=0,0,$BN24)),2) -> 135.09 | BR24: =ROUND(SUM($AP24:$AS24)/$AC24,2) -> 0 | BS24: =SUM(BO24:BR24) -> 135.09 | BU24: =SUM(AD24:AG24)+SUM(BF24:BH24) -> 135.09 | BV24: =SUM(N24:U24) -> 135.09 | BW24: =SUM(AP24:AS24) -> 0 | BX24: =SUM(AD24,AE24,AF24) -> 0 | BY24: =BU24-BV24 -> 0 | BZ24: =N24+P24+Q24+R24+S24+T24+U24 -> 135.09 | CA24: Domestic | CB24: =IF(SUM(AD24:AJ24)=0,"Equity","Debt") -> Equity | CC24: =IF(RIGHT(CV24,4)="(GP)","General Partners",IF(RIGHT(CV24,5)="(ALP)","GP Excess",CV24)) -> LP SCH A 5 | CD24: =F24&"_"&AV24 -> SCH A Legal Entity 9_Deal 3 | CE24: =B24&"_"&G24&"_"&E24 -> Deal 3_Partner 5_Partnership 8 | CF24: =IFERROR(VLOOKUP(CE24,[1]Mapping!A:E,5,0),"") | CG24: Deal 3 | CO24: =IF(FM24<>"",FM24,FJ24) -> 0 | CV24: LP SCH A 5 | CX24: Deal 3
A25: 45382 | B25: =IFERROR(VLOOKUP(CG25,CH:CI,2,0),CG25) -> Deal 3 | C25: Tranche 3 | D25: Position 3 | E25: Partnership 9 | F25: SCH A Legal Entity 10 | G25: Partner 7 | H25: =IF(CF25<>"",CF25,CC25) -> LP SCH A 7 | I25: Partner ID 10 | J25: USD | K25: Vehicle 10 | L25: Income | N25: 0 | O25: 0 | P25: 0 | Q25: 0 | R25: 0 | S25: 0 | T25: 69.49 | U25: 0 | V25: 0 | W25: 0 | X25: 0 | Y25: 0 | Z25: 69.49 | AA25: 0 | AB25: 1 | AC25: 1 | AD25: 0 | AE25: 0 | AF25: 0 | AG25: 0 | AH25: 0 | AI25: 0 | AJ25: 0 | AK25: 69.49 | AL25: 0 | AM25: 0 | AN25: 0 | AO25: 0 | AP25: 0 | AQ25: 0 | AR25: 0 | AS25: 0 | AT25: =VLOOKUP(H25,Control!B:C,2,0) -> 7 | AV25: =IFERROR(VLOOKUP($B25,'[1]Accounts - MDM Data'!$N$1:$O$5,2,0),$B25) -> Deal 3 | AW25: =VLOOKUP(H25,'[1]Accounts - MDM Data'!$H$2:$I$8,2,FALSE) -> #N/A | AX25: =N25 -> 0 | AY25: =P25 -> 0 | AZ25: =Q25 -> 0 | BA25: =R25 -> 0 | BB25: =T25 -> 69.49 | BC25: =S25+U25 -> 0 | BD25: =SUM(AD25:AF25) -> 0 | BE25: =SUM(AG25:AI25) -> 0 | BF25: =IF($M25="Yes",0,IF(ISNUMBER(SEARCH("LH",F25)),SUM($AM25+$AN25),IF($N25=0,SUM(AF25+AG25+AH25+AM25+AN25),$N25))) -> 0 | BG25: =IF($M25="Yes",0,IF(ISNUMBER(SEARCH("LH",F25)),$AL25,IF(SUM($P25:$S25)=0,SUM(AE25+AI25+AL25),SUM($P25:$S25)))) -> 0 | BH25: =IF(M25="yes",0,IF(ISNUMBER(SEARCH("LH",F25)),AK25,IF(SUM(T25+U25)=0,SUM(AD25+AK25),SUM(T25+U25)))) -> 69.49 | BI25: =ROUND(SUM($AP25:$AS25),2) -> 0 | BJ25: =SUM(BD25:BH25)+SUM(AO25:AS25)+O25 -> 69.49 | BK25: =ROUND($AX25/$AB25,2) -> 0 | BL25: =ROUND(SUM($AY25:$BA25)/$AC25+($AX25/$AC25-$BK25),2) -> 0 | BM25: =ROUND($BB25/$AC25,2) -> 69.49 | BN25: =ROUND($BC25/$AC25,2) -> 0 | BO25: =ROUND($BF25/AB25,2) -> 0 | BP25: =ROUND(IF($BL25=0,0,$BL25+IF($S25=0,0,$BN25)),2) -> 0 | BQ25: =ROUND(IF($BM25=0,0,$BM25+IF($U25=0,0,$BN25)),2) -> 69.49 | BR25: =ROUND(SUM($AP25:$AS25)/$AC25,2) -> 0 | BS25: =SUM(BO25:BR25) -> 69.49 | BU25: =SUM(AD25:AG25)+SUM(BF25:BH25) -> 69.49 | BV25: =SUM(N25:U25) -> 69.49 | BW25: =SUM(AP25:AS25) -> 0 | BX25: =SUM(AD25,AE25,AF25) -> 0 | BY25: =BU25-BV25 -> 0 | BZ25: =N25+P25+Q25+R25+S25+T25+U25 -> 69.49 | CA25: Domestic | CB25: =IF(SUM(AD25:AJ25)=0,"Equity","Debt") -> Equity | CC25: =IF(RIGHT(CV25,4)="(GP)","General Partners",IF(RIGHT(CV25,5)="(ALP)","GP Excess",CV25)) -> LP SCH A 7 | CD25: =F25&"_"&AV25 -> SCH A Legal Entity 10_Deal 3 | CE25: =B25&"_"&G25&"_"&E25 -> Deal 3_Partner 7_Partnership 9 | CF25: =IFERROR(VLOOKUP(CE25,[1]Mapping!A:E,5,0),"") | CG25: Deal 3 | CO25: =IF(FM25<>"",FM25,FJ25) -> 0 | CV25: LP SCH A 7 | CX25: Deal 3
A26: 45382 | B26: =IFERROR(VLOOKUP(CG26,CH:CI,2,0),CG26) -> Deal 3 | C26: Tranche 3 | D26: Position 3 | E26: Partnership 5 | F26: SCH A Legal Entity 13 | G26: Partner 3 | H26: =IF(CF26<>"",CF26,CC26) -> LP SCH A 3 | I26: Partner ID 13 | J26: USD | K26: Vehicle 13 | L26: Income | M26: Yes | N26: 0 | O26: 0 | P26: 0 | Q26: 0 | R26: 0 | S26: 0 | T26: 794.95 | U26: 0 | V26: 0 | W26: 0 | X26: 0 | Y26: 0 | Z26: 794.95 | AA26: 0 | AB26: 1 | AC26: 1 | AD26: 0 | AE26: 0 | AF26: 0 | AG26: 0 | AH26: 0 | AI26: 0 | AJ26: 0 | AK26: 0 | AL26: 0 | AM26: 0 | AN26: 0 | AO26: 0 | AP26: 0 | AQ26: 0 | AR26: 0 | AS26: 0 | AT26: =VLOOKUP(H26,Control!B:C,2,0) -> 3 | AV26: =IFERROR(VLOOKUP($B26,'[1]Accounts - MDM Data'!$N$1:$O$5,2,0),$B26) -> Deal 3 | AW26: =VLOOKUP(H26,'[1]Accounts - MDM Data'!$H$2:$I$8,2,FALSE) -> #N/A | AX26: =N26 -> 0 | AY26: =P26 -> 0 | AZ26: =Q26 -> 0 | BA26: =R26 -> 0 | BB26: =T26 -> 794.95 | BC26: =S26+U26 -> 0 | BD26: =SUM(AD26:AF26) -> 0 | BE26: =SUM(AG26:AI26) -> 0 | BF26: =IF($M26="Yes",0,IF(ISNUMBER(SEARCH("LH",F26)),SUM($AM26+$AN26),IF($N26=0,SUM(AF26+AG26+AH26+AM26+AN26),$N26))) -> 0 | BG26: =IF($M26="Yes",0,IF(ISNUMBER(SEARCH("LH",F26)),$AL26,IF(SUM($P26:$S26)=0,SUM(AE26+AI26+AL26),SUM($P26:$S26)))) -> 0 | BH26: =IF(M26="yes",0,IF(ISNUMBER(SEARCH("LH",F26)),AK26,IF(SUM(T26+U26)=0,SUM(AD26+AK26),SUM(T26+U26)))) -> 0 | BI26: =ROUND(SUM($AP26:$AS26),2) -> 0 | BJ26: =SUM(BD26:BH26)+SUM(AO26:AS26)+O26 -> 0 | BK26: =ROUND($AX26/$AB26,2) -> 0 | BL26: =ROUND(SUM($AY26:$BA26)/$AC26+($AX26/$AC26-$BK26),2) -> 0 | BM26: =ROUND($BB26/$AC26,2) -> 794.95 | BN26: =ROUND($BC26/$AC26,2) -> 0 | BO26: =ROUND($BF26/AB26,2) -> 0 | BP26: =ROUND(IF($BL26=0,0,$BL26+IF($S26=0,0,$BN26)),2) -> 0 | BQ26: =ROUND(IF($BM26=0,0,$BM26+IF($U26=0,0,$BN26)),2) -> 794.95 | BR26: =ROUND(SUM($AP26:$AS26)/$AC26,2) -> 0 | BS26: =SUM(BO26:BR26) -> 794.95 | BU26: =SUM(AD26:AG26)+SUM(BF26:BH26) -> 0 | BV26: =SUM(N26:U26) -> 794.95 | BW26: =SUM(AP26:AS26) -> 0 | BX26: =SUM(AD26,AE26,AF26) -> 0 | BY26: =BU26-BV26 -> -794.95 | BZ26: =N26+P26+Q26+R26+S26+T26+U26 -> 794.95 | CA26: Domestic | CB26: =IF(SUM(AD26:AJ26)=0,"Equity","Debt") -> Equity | CC26: =IF(RIGHT(CV26,4)="(GP)","General Partners",IF(RIGHT(CV26,5)="(ALP)","GP Excess",CV26)) -> LP SCH A 3 | CD26: =F26&"_"&AV26 -> SCH A Legal Entity 13_Deal 3 | CE26: =B26&"_"&G26&"_"&E26 -> Deal 3_Partner 3_Partnership 5 | CF26: =IFERROR(VLOOKUP(CE26,[1]Mapping!A:E,5,0),"") | CG26: Deal 3 | CO26: =IF(FM26<>"",FM26,FJ26) -> 0 | CV26: LP SCH A 3 | CX26: Deal 3
A27: 45382 | B27: =IFERROR(VLOOKUP(CG27,CH:CI,2,0),CG27) -> Deal 3 | C27: Tranche 3 | D27: Position 3 | E27: Partnership 4 | F27: SCH A Legal Entity 13 | G27: Partner 2 | H27: =IF(CF27<>"",CF27,CC27) -> LP SCH A 2 | I27: Partner ID 13 | J27: USD | K27: Vehicle 13 | L27: Income | M27: Yes | N27: 0 | O27: 0 | P27: 0 | Q27: 0 | R27: 0 | S27: 0 | T27: 2316.28 | U27: 0 | V27: 0 | W27: 0 | X27: 0 | Y27: 0 | Z27: 2316.28 | AA27: 0 | AB27: 1 | AC27: 1 | AD27: 0 | AE27: 0 | AF27: 0 | AG27: 0 | AH27: 0 | AI27: 0 | AJ27: 0 | AK27: 0 | AL27: 0 | AM27: 0 | AN27: 0 | AO27: 0 | AP27: 0 | AQ27: 0 | AR27: 0 | AS27: 0 | AT27: =VLOOKUP(H27,Control!B:C,2,0) -> 2 | AV27: =IFERROR(VLOOKUP($B27,'[1]Accounts - MDM Data'!$N$1:$O$5,2,0),$B27) -> Deal 3 | AW27: =VLOOKUP(H27,'[1]Accounts - MDM Data'!$H$2:$I$8,2,FALSE) -> #N/A | AX27: =N27 -> 0 | AY27: =P27 -> 0 | AZ27: =Q27 -> 0 | BA27: =R27 -> 0 | BB27: =T27 -> 2316.28 | BC27: =S27+U27 -> 0 | BD27: =SUM(AD27:AF27) -> 0 | BE27: =SUM(AG27:AI27) -> 0 | BF27: =IF($M27="Yes",0,IF(ISNUMBER(SEARCH("LH",F27)),SUM($AM27+$AN27),IF($N27=0,SUM(AF27+AG27+AH27+AM27+AN27),$N27))) -> 0 | BG27: =IF($M27="Yes",0,IF(ISNUMBER(SEARCH("LH",F27)),$AL27,IF(SUM($P27:$S27)=0,SUM(AE27+AI27+AL27),SUM($P27:$S27)))) -> 0 | BH27: =IF(M27="yes",0,IF(ISNUMBER(SEARCH("LH",F27)),AK27,IF(SUM(T27+U27)=0,SUM(AD27+AK27),SUM(T27+U27)))) -> 0 | BI27: =ROUND(SUM($AP27:$AS27),2) -> 0 | BJ27: =SUM(BD27:BH27)+SUM(AO27:AS27)+O27 -> 0 | BK27: =ROUND($AX27/$AB27,2) -> 0 | BL27: =ROUND(SUM($AY27:$BA27)/$AC27+($AX27/$AC27-$BK27),2) -> 0 | BM27: =ROUND($BB27/$AC27,2) -> 2316.28 | BN27: =ROUND($BC27/$AC27,2) -> 0 | BO27: =ROUND($BF27/AB27,2) -> 0 | BP27: =ROUND(IF($BL27=0,0,$BL27+IF($S27=0,0,$BN27)),2) -> 0 | BQ27: =ROUND(IF($BM27=0,0,$BM27+IF($U27=0,0,$BN27)),2) -> 2316.28 | BR27: =ROUND(SUM($AP27:$AS27)/$AC27,2) -> 0 | BS27: =SUM(BO27:BR27) -> 2316.28 | BU27: =SUM(AD27:AG27)+SUM(BF27:BH27) -> 0 | BV27: =SUM(N27:U27) -> 2316.28 | BW27: =SUM(AP27:AS27) -> 0 | BX27: =SUM(AD27,AE27,AF27) -> 0 | BY27: =BU27-BV27 -> -2316.28 | BZ27: =N27+P27+Q27+R27+S27+T27+U27 -> 2316.28 | CA27: Domestic | CB27: =IF(SUM(AD27:AJ27)=0,"Equity","Debt") -> Equity | CC27: =IF(RIGHT(CV27,4)="(GP)","General Partners",IF(RIGHT(CV27,5)="(ALP)","GP Excess",CV27)) -> LP SCH A 2 | CD27: =F27&"_"&AV27 -> SCH A Legal Entity 13_Deal 3 | CE27: =B27&"_"&G27&"_"&E27 -> Deal 3_Partner 2_Partnership 4 | CF27: =IFERROR(VLOOKUP(CE27,[1]Mapping!A:E,5,0),"") | CG27: Deal 3 | CO27: =IF(FM27<>"",FM27,FJ27) -> 0 | CV27: LP SCH A 2 | CX27: Deal 3
A28: 45382 | B28: =IFERROR(VLOOKUP(CG28,CH:CI,2,0),CG28) -> Deal 3 | C28: Tranche 3 | D28: Position 3 | E28: Partnership 4 | F28: SCH A Legal Entity 13 | G28: Partner 1 | H28: =IF(CF28<>"",CF28,CC28) -> LP SCH A 1 | I28: Partner ID 13 | J28: USD | K28: Vehicle 13 | L28: Income | M28: Yes | N28: 0 | O28: 0 | P28: 0 | Q28: 0 | R28: 0 | S28: 0 | T28: 101.92 | U28: 0 | V28: 0 | W28: 0 | X28: 0 | Y28: 0 | Z28: 101.92 | AA28: 0 | AB28: 1 | AC28: 1 | AD28: 0 | AE28: 0 | AF28: 0 | AG28: 0 | AH28: 0 | AI28: 0 | AJ28: 0 | AK28: 0 | AL28: 0 | AM28: 0 | AN28: 0 | AO28: 0 | AP28: 0 | AQ28: 0 | AR28: 0 | AS28: 0 | AT28: =VLOOKUP(H28,Control!B:C,2,0) -> 1 | AV28: =IFERROR(VLOOKUP($B28,'[1]Accounts - MDM Data'!$N$1:$O$5,2,0),$B28) -> Deal 3 | AW28: =VLOOKUP(H28,'[1]Accounts - MDM Data'!$H$2:$I$8,2,FALSE) -> #N/A | AX28: =N28 -> 0 | AY28: =P28 -> 0 | AZ28: =Q28 -> 0 | BA28: =R28 -> 0 | BB28: =T28 -> 101.92 | BC28: =S28+U28 -> 0 | BD28: =SUM(AD28:AF28) -> 0 | BE28: =SUM(AG28:AI28) -> 0 | BF28: =IF($M28="Yes",0,IF(ISNUMBER(SEARCH("LH",F28)),SUM($AM28+$AN28),IF($N28=0,SUM(AF28+AG28+AH28+AM28+AN28),$N28))) -> 0 | BG28: =IF($M28="Yes",0,IF(ISNUMBER(SEARCH("LH",F28)),$AL28,IF(SUM($P28:$S28)=0,SUM(AE28+AI28+AL28),SUM($P28:$S28)))) -> 0 | BH28: =IF(M28="yes",0,IF(ISNUMBER(SEARCH("LH",F28)),AK28,IF(SUM(T28+U28)=0,SUM(AD28+AK28),SUM(T28+U28)))) -> 0 | BI28: =ROUND(SUM($AP28:$AS28),2) -> 0 | BJ28: =SUM(BD28:BH28)+SUM(AO28:AS28)+O28 -> 0 | BK28: =ROUND($AX28/$AB28,2) -> 0 | BL28: =ROUND(SUM($AY28:$BA28)/$AC28+($AX28/$AC28-$BK28),2) -> 0 | BM28: =ROUND($BB28/$AC28,2) -> 101.92 | BN28: =ROUND($BC28/$AC28,2) -> 0 | BO28: =ROUND($BF28/AB28,2) -> 0 | BP28: =ROUND(IF($BL28=0,0,$BL28+IF($S28=0,0,$BN28)),2) -> 0 | BQ28: =ROUND(IF($BM28=0,0,$BM28+IF($U28=0,0,$BN28)),2) -> 101.92 | BR28: =ROUND(SUM($AP28:$AS28)/$AC28,2) -> 0 | BS28: =SUM(BO28:BR28) -> 101.92 | BU28: =SUM(AD28:AG28)+SUM(BF28:BH28) -> 0 | BV28: =SUM(N28:U28) -> 101.92 | BW28: =SUM(AP28:AS28) -> 0 | BX28: =SUM(AD28,AE28,AF28) -> 0 | BY28: =BU28-BV28 -> -101.92 | BZ28: =N28+P28+Q28+R28+S28+T28+U28 -> 101.92 | CA28: Domestic | CB28: =IF(SUM(AD28:AJ28)=0,"Equity","Debt") -> Equity | CC28: =IF(RIGHT(CV28,4)="(GP)","General Partners",IF(RIGHT(CV28,5)="(ALP)","GP Excess",CV28)) -> LP SCH A 1 | CD28: =F28&"_"&AV28 -> SCH A Legal Entity 13_Deal 3 | CE28: =B28&"_"&G28&"_"&E28 -> Deal 3_Partner 1_Partnership 4 | CF28: =IFERROR(VLOOKUP(CE28,[1]Mapping!A:E,5,0),"") | CG28: Deal 3 | CO28: =IF(FM28<>"",FM28,FJ28) -> 0 | CV28: LP SCH A 1 | CX28: Deal 3
A29: 45382 | B29: =IFERROR(VLOOKUP(CG29,CH:CI,2,0),CG29) -> Deal 3 | C29: Tranche 3 | D29: Position 3 | E29: Partnership 12 | F29: SCH A Legal Entity 7 | G29: Partner 1 | H29: =IF(CF29<>"",CF29,CC29) -> LP SCH A 1 | I29: Partner ID 7 | J29: USD | K29: Vehicle 7 | L29: Income | N29: 0 | O29: 0 | P29: 0 | Q29: 0 | R29: 0 | S29: 0 | T29: 0 | U29: 0 | V29: 0 | W29: 0 | X29: 0 | Y29: 0 | Z29: 0 | AA29: 0 | AB29: 1 | AC29: 1 | AD29: 101.92 | AE29: 0 | AF29: 0 | AG29: 0 | AH29: 0 | AI29: 0 | AJ29: 0 | AK29: 0 | AL29: 0 | AM29: 0 | AN29: 0 | AO29: 0 | AP29: 0 | AQ29: 0 | AR29: 0 | AS29: 0 | AT29: =VLOOKUP(H29,Control!B:C,2,0) -> 1 | AV29: =IFERROR(VLOOKUP($B29,'[1]Accounts - MDM Data'!$N$1:$O$5,2,0),$B29) -> Deal 3 | AW29: =VLOOKUP(H29,'[1]Accounts - MDM Data'!$H$2:$I$8,2,FALSE) -> #N/A | AX29: =N29 -> 0 | AY29: =P29 -> 0 | AZ29: =Q29 -> 0 | BA29: =R29 -> 0 | BB29: =T29 -> 0 | BC29: =S29+U29 -> 0 | BD29: =SUM(AD29:AF29) -> 101.92 | BE29: =SUM(AG29:AI29) -> 0 | BF29: =IF($M29="Yes",0,IF(ISNUMBER(SEARCH("LH",F29)),SUM($AM29+$AN29),IF($N29=0,SUM(AF29+AG29+AH29+AM29+AN29),$N29))) -> 0 | BG29: =IF($M29="Yes",0,IF(ISNUMBER(SEARCH("LH",F29)),$AL29,IF(SUM($P29:$S29)=0,SUM(AE29+AI29+AL29),SUM($P29:$S29)))) -> 0 | BH29: =IF(M29="yes",0,IF(ISNUMBER(SEARCH("LH",F29)),AK29,IF(SUM(T29+U29)=0,SUM(AD29+AK29),SUM(T29+U29)))) -> 101.92 | BI29: =ROUND(SUM($AP29:$AS29),2) -> 0 | BJ29: =SUM(BD29:BH29)+SUM(AO29:AS29)+O29 -> 203.84 | BK29: =ROUND($AX29/$AB29,2) -> 0 | BL29: =ROUND(SUM($AY29:$BA29)/$AC29+($AX29/$AC29-$BK29),2) -> 0 | BM29: =ROUND($BB29/$AC29,2) -> 0 | BN29: =ROUND($BC29/$AC29,2) -> 0 | BO29: =ROUND($BF29/AB29,2) -> 0 | BP29: =ROUND(IF($BL29=0,0,$BL29+IF($S29=0,0,$BN29)),2) -> 0 | BQ29: =ROUND(IF($BM29=0,0,$BM29+IF($U29=0,0,$BN29)),2) -> 0 | BR29: =ROUND(SUM($AP29:$AS29)/$AC29,2) -> 0 | BS29: =SUM(BO29:BR29) -> 0 | BU29: =SUM(AD29:AG29)+SUM(BF29:BH29) -> 203.84 | BV29: =SUM(N29:U29) -> 0 | BW29: =SUM(AP29:AS29) -> 0 | BX29: =SUM(AD29,AE29,AF29) -> 101.92 | BY29: =BU29-BV29 -> 203.84 | BZ29: =N29+P29+Q29+R29+S29+T29+U29 -> 0 | CA29: Domestic | CB29: =IF(SUM(AD29:AJ29)=0,"Equity","Debt") -> Debt | CC29: =IF(RIGHT(CV29,4)="(GP)","General Partners",IF(RIGHT(CV29,5)="(ALP)","GP Excess",CV29)) -> LP SCH A 1 | CD29: =F29&"_"&AV29 -> SCH A Legal Entity 7_Deal 3 | CE29: =B29&"_"&G29&"_"&E29 -> Deal 3_Partner 1_Partnership 12 | CF29: =IFERROR(VLOOKUP(CE29,[1]Mapping!A:E,5,0),"") | CG29: Deal 3 | CO29: =IF(FM29<>"",FM29,FJ29) -> 0 | CV29: LP SCH A 1 | CX29: Deal 3
A30: 45382 | B30: =IFERROR(VLOOKUP(CG30,CH:CI,2,0),CG30) -> Deal 3 | C30: Tranche 3 | D30: Position 3 | E30: Partnership 12 | F30: SCH A Legal Entity 8 | G30: Partner 2 | H30: =IF(CF30<>"",CF30,CC30) -> LP SCH A 2 | I30: Partner ID 8 | J30: USD | K30: Vehicle 8 | L30: Income | N30: 0 | O30: 0 | P30: 0 | Q30: 0 | R30: 0 | S30: 0 | T30: 0 | U30: 0 | V30: 0 | W30: 0 | X30: 0 | Y30: 0 | Z30: 0 | AA30: 0 | AB30: 1 | AC30: 1 | AD30: 2316.28 | AE30: 0 | AF30: 0 | AG30: 0 | AH30: 0 | AI30: 0 | AJ30: 0 | AK30: 0 | AL30: 0 | AM30: 0 | AN30: 0 | AO30: 0 | AP30: 0 | AQ30: 0 | AR30: 0 | AS30: 0 | AT30: =VLOOKUP(H30,Control!B:C,2,0) -> 2 | AV30: =IFERROR(VLOOKUP($B30,'[1]Accounts - MDM Data'!$N$1:$O$5,2,0),$B30) -> Deal 3 | AW30: =VLOOKUP(H30,'[1]Accounts - MDM Data'!$H$2:$I$8,2,FALSE) -> #N/A | AX30: =N30 -> 0 | AY30: =P30 -> 0 | AZ30: =Q30 -> 0 | BA30: =R30 -> 0 | BB30: =T30 -> 0 | BC30: =S30+U30 -> 0 | BD30: =SUM(AD30:AF30) -> 2316.28 | BE30: =SUM(AG30:AI30) -> 0 | BF30: =IF($M30="Yes",0,IF(ISNUMBER(SEARCH("LH",F30)),SUM($AM30+$AN30),IF($N30=0,SUM(AF30+AG30+AH30+AM30+AN30),$N30))) -> 0 | BG30: =IF($M30="Yes",0,IF(ISNUMBER(SEARCH("LH",F30)),$AL30,IF(SUM($P30:$S30)=0,SUM(AE30+AI30+AL30),SUM($P30:$S30)))) -> 0 | BH30: =IF(M30="yes",0,IF(ISNUMBER(SEARCH("LH",F30)),AK30,IF(SUM(T30+U30)=0,SUM(AD30+AK30),SUM(T30+U30)))) -> 2316.28 | BI30: =ROUND(SUM($AP30:$AS30),2) -> 0 | BJ30: =SUM(BD30:BH30)+SUM(AO30:AS30)+O30 -> 4632.56 | BK30: =ROUND($AX30/$AB30,2) -> 0 | BL30: =ROUND(SUM($AY30:$BA30)/$AC30+($AX30/$AC30-$BK30),2) -> 0 | BM30: =ROUND($BB30/$AC30,2) -> 0 | BN30: =ROUND($BC30/$AC30,2) -> 0 | BO30: =ROUND($BF30/AB30,2) -> 0 | BP30: =ROUND(IF($BL30=0,0,$BL30+IF($S30=0,0,$BN30)),2) -> 0 | BQ30: =ROUND(IF($BM30=0,0,$BM30+IF($U30=0,0,$BN30)),2) -> 0 | BR30: =ROUND(SUM($AP30:$AS30)/$AC30,2) -> 0 | BS30: =SUM(BO30:BR30) -> 0 | BU30: =SUM(AD30:AG30)+SUM(BF30:BH30) -> 4632.56 | BV30: =SUM(N30:U30) -> 0 | BW30: =SUM(AP30:AS30) -> 0 | BX30: =SUM(AD30,AE30,AF30) -> 2316.28 | BY30: =BU30-BV30 -> 4632.56 | BZ30: =N30+P30+Q30+R30+S30+T30+U30 -> 0 | CA30: Domestic | CB30: =IF(SUM(AD30:AJ30)=0,"Equity","Debt") -> Debt | CC30: =IF(RIGHT(CV30,4)="(GP)","General Partners",IF(RIGHT(CV30,5)="(ALP)","GP Excess",CV30)) -> LP SCH A 2 | CD30: =F30&"_"&AV30 -> SCH A Legal Entity 8_Deal 3 | CE30: =B30&"_"&G30&"_"&E30 -> Deal 3_Partner 2_Partnership 12 | CF30: =IFERROR(VLOOKUP(CE30,[1]Mapping!A:E,5,0),"") | CG30: Deal 3 | CO30: =IF(FM30<>"",FM30,FJ30) -> 0 | CV30: LP SCH A 2 | CX30: Deal 3
A31: 45382 | B31: =IFERROR(VLOOKUP(CG31,CH:CI,2,0),CG31) -> Deal 3 | C31: Tranche 3 | D31: Position 3 | E31: Partnership 12 | F31: SCH A Legal Entity 3 | G31: Partner 3 | H31: =IF(CF31<>"",CF31,CC31) -> LP SCH A 3 | I31: Partner ID 3 | J31: USD | K31: Vehicle 3 | L31: Income | N31: 0 | O31: 0 | P31: 0 | Q31: 0 | R31: 0 | S31: 0 | T31: 0 | U31: 0 | V31: 0 | W31: 0 | X31: 0 | Y31: 0 | Z31: 0 | AA31: 0 | AB31: 1 | AC31: 1 | AD31: 794.95 | AE31: 0 | AF31: 0 | AG31: 0 | AH31: 0 | AI31: 0 | AJ31: 0 | AK31: 0 | AL31: 0 | AM31: 0 | AN31: 0 | AO31: 0 | AP31: 0 | AQ31: 0 | AR31: 0 | AS31: 0 | AT31: =VLOOKUP(H31,Control!B:C,2,0) -> 3 | AV31: =IFERROR(VLOOKUP($B31,'[1]Accounts - MDM Data'!$N$1:$O$5,2,0),$B31) -> Deal 3 | AW31: =VLOOKUP(H31,'[1]Accounts - MDM Data'!$H$2:$I$8,2,FALSE) -> #N/A | AX31: =N31 -> 0 | AY31: =P31 -> 0 | AZ31: =Q31 -> 0 | BA31: =R31 -> 0 | BB31: =T31 -> 0 | BC31: =S31+U31 -> 0 | BD31: =SUM(AD31:AF31) -> 794.95 | BE31: =SUM(AG31:AI31) -> 0 | BF31: =IF($M31="Yes",0,IF(ISNUMBER(SEARCH("LH",F31)),SUM($AM31+$AN31),IF($N31=0,SUM(AF31+AG31+AH31+AM31+AN31),$N31))) -> 0 | BG31: =IF($M31="Yes",0,IF(ISNUMBER(SEARCH("LH",F31)),$AL31,IF(SUM($P31:$S31)=0,SUM(AE31+AI31+AL31),SUM($P31:$S31)))) -> 0 | BH31: =IF(M31="yes",0,IF(ISNUMBER(SEARCH("LH",F31)),AK31,IF(SUM(T31+U31)=0,SUM(AD31+AK31),SUM(T31+U31)))) -> 794.95 | BI31: =ROUND(SUM($AP31:$AS31),2) -> 0 | BJ31: =SUM(BD31:BH31)+SUM(AO31:AS31)+O31 -> 1589.9 | BK31: =ROUND($AX31/$AB31,2) -> 0 | BL31: =ROUND(SUM($AY31:$BA31)/$AC31+($AX31/$AC31-$BK31),2) -> 0 | BM31: =ROUND($BB31/$AC31,2) -> 0 | BN31: =ROUND($BC31/$AC31,2) -> 0 | BO31: =ROUND($BF31/AB31,2) -> 0 | BP31: =ROUND(IF($BL31=0,0,$BL31+IF($S31=0,0,$BN31)),2) -> 0 | BQ31: =ROUND(IF($BM31=0,0,$BM31+IF($U31=0,0,$BN31)),2) -> 0 | BR31: =ROUND(SUM($AP31:$AS31)/$AC31,2) -> 0 | BS31: =SUM(BO31:BR31) -> 0 | BU31: =SUM(AD31:AG31)+SUM(BF31:BH31) -> 1589.9 | BV31: =SUM(N31:U31) -> 0 | BW31: =SUM(AP31:AS31) -> 0 | BX31: =SUM(AD31,AE31,AF31) -> 794.95 | BY31: =BU31-BV31 -> 1589.9 | BZ31: =N31+P31+Q31+R31+S31+T31+U31 -> 0 | CA31: Domestic | CB31: =IF(SUM(AD31:AJ31)=0,"Equity","Debt") -> Debt | CC31: =IF(RIGHT(CV31,4)="(GP)","General Partners",IF(RIGHT(CV31,5)="(ALP)","GP Excess",CV31)) -> LP SCH A 3 | CD31: =F31&"_"&AV31 -> SCH A Legal Entity 3_Deal 3 | CE31: =B31&"_"&G31&"_"&E31 -> Deal 3_Partner 3_Partnership 12 | CF31: =IFERROR(VLOOKUP(CE31,[1]Mapping!A:E,5,0),"") | CG31: Deal 3 | CO31: =IF(FM31<>"",FM31,FJ31) -> 0 | CV31: LP SCH A 3 | CX31: Deal 3
A32: 45382 | B32: =IFERROR(VLOOKUP(CG32,CH:CI,2,0),CG32) -> Deal 4 | C32: Tranche 4 | D32: Position 4 | E32: Partnership 2 | F32: SCH A Legal Entity 4 | G32: Partner 5 | H32: =IF(CF32<>"",CF32,CC32) -> LP SCH A 5 | I32: Partner ID 4 | J32: USD | K32: Vehicle 4 | L32: Income | N32: 0 | O32: 0 | P32: 0 | Q32: 0 | R32: 0 | S32: 0 | T32: 305.98 | U32: 0 | V32: 0 | W32: 0 | X32: 0 | Y32: 0 | Z32: 305.98 | AA32: 0 | AB32: 1 | AC32: 1 | AD32: 0 | AE32: 0 | AF32: 0 | AG32: 0 | AH32: 0 | AI32: 0 | AJ32: 0 | AK32: 0 | AL32: 0 | AM32: 0 | AN32: 0 | AO32: 0 | AP32: 0 | AQ32: 0 | AR32: 0 | AS32: 0 | AT32: =VLOOKUP(H32,Control!B:C,2,0) -> 5 | AV32: =IFERROR(VLOOKUP($B32,'[1]Accounts - MDM Data'!$N$1:$O$5,2,0),$B32) -> Deal 4 | AW32: =VLOOKUP(H32,'[1]Accounts - MDM Data'!$H$2:$I$8,2,FALSE) -> #N/A | AX32: =N32 -> 0 | AY32: =P32 -> 0 | AZ32: =Q32 -> 0 | BA32: =R32 -> 0 | BB32: =T32 -> 305.98 | BC32: =S32+U32 -> 0 | BD32: =SUM(AD32:AF32) -> 0 | BE32: =SUM(AG32:AI32) -> 0 | BF32: =IF($M32="Yes",0,IF(ISNUMBER(SEARCH("LH",F32)),SUM($AM32+$AN32),IF($N32=0,SUM(AF32+AG32+AH32+AM32+AN32),$N32))) -> 0 | BG32: =IF($M32="Yes",0,IF(ISNUMBER(SEARCH("LH",F32)),$AL32,IF(SUM($P32:$S32)=0,SUM(AE32+AI32+AL32),SUM($P32:$S32)))) -> 0 | BH32: =IF(M32="yes",0,IF(ISNUMBER(SEARCH("LH",F32)),AK32,IF(SUM(T32+U32)=0,SUM(AD32+AK32),SUM(T32+U32)))) -> 305.98 | BI32: =ROUND(SUM($AP32:$AS32),2) -> 0 | BJ32: =SUM(BD32:BH32)+SUM(AO32:AS32)+O32 -> 305.98 | BK32: =ROUND($AX32/$AB32,2) -> 0 | BL32: =ROUND(SUM($AY32:$BA32)/$AC32+($AX32/$AC32-$BK32),2) -> 0 | BM32: =ROUND($BB32/$AC32,2) -> 305.98 | BN32: =ROUND($BC32/$AC32,2) -> 0 | BO32: =ROUND($BF32/AB32,2) -> 0 | BP32: =ROUND(IF($BL32=0,0,$BL32+IF($S32=0,0,$BN32)),2) -> 0 | BQ32: =ROUND(IF($BM32=0,0,$BM32+IF($U32=0,0,$BN32)),2) -> 305.98 | BR32: =ROUND(SUM($AP32:$AS32)/$AC32,2) -> 0 | BS32: =SUM(BO32:BR32) -> 305.98 | BU32: =SUM(AD32:AG32)+SUM(BF32:BH32) -> 305.98 | BV32: =SUM(N32:U32) -> 305.98 | BW32: =SUM(AP32:AS32) -> 0 | BX32: =SUM(AD32,AE32,AF32) -> 0 | BY32: =BU32-BV32 -> 0 | BZ32: =N32+P32+Q32+R32+S32+T32+U32 -> 305.98 | CA32: Domestic | CB32: =IF(SUM(AD32:AJ32)=0,"Equity","Debt") -> Equity | CC32: =IF(RIGHT(CV32,4)="(GP)","General Partners",IF(RIGHT(CV32,5)="(ALP)","GP Excess",CV32)) -> LP SCH A 5 | CD32: =F32&"_"&AV32 -> SCH A Legal Entity 4_Deal 4 | CE32: =B32&"_"&G32&"_"&E32 -> Deal 4_Partner 5_Partnership 2 | CF32: =IFERROR(VLOOKUP(CE32,[1]Mapping!A:E,5,0),"") | CG32: Deal 4 | CO32: =IF(FM32<>"",FM32,FJ32) -> 0 | CV32: LP SCH A 5 | CX32: Deal 4
A33: 45382 | B33: =IFERROR(VLOOKUP(CG33,CH:CI,2,0),CG33) -> Deal 4 | C33: Tranche 5 | D33: Position 5 | E33: Partnership 2 | F33: SCH A Legal Entity 4 | G33: Partner 7 | H33: =IF(CF33<>"",CF33,CC33) -> LP SCH A 7 | I33: Partner ID 4 | J33: USD | K33: Vehicle 4 | L33: Income | N33: 0 | O33: 0 | P33: 0 | Q33: 0 | R33: 0 | S33: 0 | T33: 81.42 | U33: 0 | V33: 0 | W33: 0 | X33: 0 | Y33: 0 | Z33: 81.42 | AA33: 0 | AB33: 1 | AC33: 1 | AD33: 0 | AE33: 0 | AF33: 0 | AG33: 0 | AH33: 0 | AI33: 0 | AJ33: 0 | AK33: 0 | AL33: 0 | AM33: 0 | AN33: 0 | AO33: 0 | AP33: 0 | AQ33: 0 | AR33: 0 | AS33: 0 | AT33: =VLOOKUP(H33,Control!B:C,2,0) -> 7 | AV33: =IFERROR(VLOOKUP($B33,'[1]Accounts - MDM Data'!$N$1:$O$5,2,0),$B33) -> Deal 4 | AW33: =VLOOKUP(H33,'[1]Accounts - MDM Data'!$H$2:$I$8,2,FALSE) -> #N/A | AX33: =N33 -> 0 | AY33: =P33 -> 0 | AZ33: =Q33 -> 0 | BA33: =R33 -> 0 | BB33: =T33 -> 81.42 | BC33: =S33+U33 -> 0 | BD33: =SUM(AD33:AF33) -> 0 | BE33: =SUM(AG33:AI33) -> 0 | BF33: =IF($M33="Yes",0,IF(ISNUMBER(SEARCH("LH",F33)),SUM($AM33+$AN33),IF($N33=0,SUM(AF33+AG33+AH33+AM33+AN33),$N33))) -> 0 | BG33: =IF($M33="Yes",0,IF(ISNUMBER(SEARCH("LH",F33)),$AL33,IF(SUM($P33:$S33)=0,SUM(AE33+AI33+AL33),SUM($P33:$S33)))) -> 0 | BH33: =IF(M33="yes",0,IF(ISNUMBER(SEARCH("LH",F33)),AK33,IF(SUM(T33+U33)=0,SUM(AD33+AK33),SUM(T33+U33)))) -> 81.42 | BI33: =ROUND(SUM($AP33:$AS33),2) -> 0 | BJ33: =SUM(BD33:BH33)+SUM(AO33:AS33)+O33 -> 81.42 | BK33: =ROUND($AX33/$AB33,2) -> 0 | BL33: =ROUND(SUM($AY33:$BA33)/$AC33+($AX33/$AC33-$BK33),2) -> 0 | BM33: =ROUND($BB33/$AC33,2) -> 81.42 | BN33: =ROUND($BC33/$AC33,2) -> 0 | BO33: =ROUND($BF33/AB33,2) -> 0 | BP33: =ROUND(IF($BL33=0,0,$BL33+IF($S33=0,0,$BN33)),2) -> 0 | BQ33: =ROUND(IF($BM33=0,0,$BM33+IF($U33=0,0,$BN33)),2) -> 81.42 | BR33: =ROUND(SUM($AP33:$AS33)/$AC33,2) -> 0 | BS33: =SUM(BO33:BR33) -> 81.42 | BU33: =SUM(AD33:AG33)+SUM(BF33:BH33) -> 81.42 | BV33: =SUM(N33:U33) -> 81.42 | BW33: =SUM(AP33:AS33) -> 0 | BX33: =SUM(AD33,AE33,AF33) -> 0 | BY33: =BU33-BV33 -> 0 | BZ33: =N33+P33+Q33+R33+S33+T33+U33 -> 81.42 | CA33: Domestic | CB33: =IF(SUM(AD33:AJ33)=0,"Equity","Debt") -> Equity | CC33: =IF(RIGHT(CV33,4)="(GP)","General Partners",IF(RIGHT(CV33,5)="(ALP)","GP Excess",CV33)) -> LP SCH A 7 | CD33: =F33&"_"&AV33 -> SCH A Legal Entity 4_Deal 4 | CE33: =B33&"_"&G33&"_"&E33 -> Deal 4_Partner 7_Partnership 2 | CF33: =IFERROR(VLOOKUP(CE33,[1]Mapping!A:E,5,0),"") | CG33: Deal 4 | CO33: =IF(FM33<>"",FM33,FJ33) -> 0 | CV33: LP SCH A 7 | CX33: Deal 4
A34: 45382 | B34: =IFERROR(VLOOKUP(CG34,CH:CI,2,0),CG34) -> Deal 4 | C34: Tranche 5 | D34: Position 5 | E34: Partnership 2 | F34: SCH A Legal Entity 4 | G34: Partner 5 | H34: =IF(CF34<>"",CF34,CC34) -> LP SCH A 5 | I34: Partner ID 4 | J34: USD | K34: Vehicle 4 | L34: Income | N34: 0 | O34: 0 | P34: 0 | Q34: 0 | R34: 0 | S34: 0 | T34: 158.28 | U34: 0 | V34: 0 | W34: 0 | X34: 0 | Y34: 0 | Z34: 158.28 | AA34: 0 | AB34: 1 | AC34: 1 | AD34: 0 | AE34: 0 | AF34: 0 | AG34: 0 | AH34: 0 | AI34: 0 | AJ34: 0 | AK34: 0 | AL34: 0 | AM34: 0 | AN34: 0 | AO34: 0 | AP34: 0 | AQ34: 0 | AR34: 0 | AS34: 0 | AT34: =VLOOKUP(H34,Control!B:C,2,0) -> 5 | AV34: =IFERROR(VLOOKUP($B34,'[1]Accounts - MDM Data'!$N$1:$O$5,2,0),$B34) -> Deal 4 | AW34: =VLOOKUP(H34,'[1]Accounts - MDM Data'!$H$2:$I$8,2,FALSE) -> #N/A | AX34: =N34 -> 0 | AY34: =P34 -> 0 | AZ34: =Q34 -> 0 | BA34: =R34 -> 0 | BB34: =T34 -> 158.28 | BC34: =S34+U34 -> 0 | BD34: =SUM(AD34:AF34) -> 0 | BE34: =SUM(AG34:AI34) -> 0 | BF34: =IF($M34="Yes",0,IF(ISNUMBER(SEARCH("LH",F34)),SUM($AM34+$AN34),IF($N34=0,SUM(AF34+AG34+AH34+AM34+AN34),$N34))) -> 0 | BG34: =IF($M34="Yes",0,IF(ISNUMBER(SEARCH("LH",F34)),$AL34,IF(SUM($P34:$S34)=0,SUM(AE34+AI34+AL34),SUM($P34:$S34)))) -> 0 | BH34: =IF(M34="yes",0,IF(ISNUMBER(SEARCH("LH",F34)),AK34,IF(SUM(T34+U34)=0,SUM(AD34+AK34),SUM(T34+U34)))) -> 158.28 | BI34: =ROUND(SUM($AP34:$AS34),2) -> 0 | BJ34: =SUM(BD34:BH34)+SUM(AO34:AS34)+O34 -> 158.28 | BK34: =ROUND($AX34/$AB34,2) -> 0 | BL34: =ROUND(SUM($AY34:$BA34)/$AC34+($AX34/$AC34-$BK34),2) -> 0 | BM34: =ROUND($BB34/$AC34,2) -> 158.28 | BN34: =ROUND($BC34/$AC34,2) -> 0 | BO34: =ROUND($BF34/AB34,2) -> 0 | BP34: =ROUND(IF($BL34=0,0,$BL34+IF($S34=0,0,$BN34)),2) -> 0 | BQ34: =ROUND(IF($BM34=0,0,$BM34+IF($U34=0,0,$BN34)),2) -> 158.28 | BR34: =ROUND(SUM($AP34:$AS34)/$AC34,2) -> 0 | BS34: =SUM(BO34:BR34) -> 158.28 | BU34: =SUM(AD34:AG34)+SUM(BF34:BH34) -> 158.28 | BV34: =SUM(N34:U34) -> 158.28 | BW34: =SUM(AP34:AS34) -> 0 | BX34: =SUM(AD34,AE34,AF34) -> 0 | BY34: =BU34-BV34 -> 0 | BZ34: =N34+P34+Q34+R34+S34+T34+U34 -> 158.28 | CA34: Domestic | CB34: =IF(SUM(AD34:AJ34)=0,"Equity","Debt") -> Equity | CC34: =IF(RIGHT(CV34,4)="(GP)","General Partners",IF(RIGHT(CV34,5)="(ALP)","GP Excess",CV34)) -> LP SCH A 5 | CD34: =F34&"_"&AV34 -> SCH A Legal Entity 4_Deal 4 | CE34: =B34&"_"&G34&"_"&E34 -> Deal 4_Partner 5_Partnership 2 | CF34: =IFERROR(VLOOKUP(CE34,[1]Mapping!A:E,5,0),"") | CG34: Deal 4 | CO34: =IF(FM34<>"",FM34,FJ34) -> 0 | CV34: LP SCH A 5 | CX34: Deal 4
A35: 45382 | B35: =IFERROR(VLOOKUP(CG35,CH:CI,2,0),CG35) -> Deal 4 | C35: Tranche 6 | D35: Position 6 | E35: Partnership 2 | F35: SCH A Legal Entity 4 | G35: Partner 5 | H35: =IF(CF35<>"",CF35,CC35) -> LP SCH A 5 | I35: Partner ID 4 | J35: USD | K35: Vehicle 4 | L35: Income | N35: 0 | O35: 0 | P35: 0 | Q35: 0 | R35: 0 | S35: 0 | T35: 35.29 | U35: 0 | V35: 0 | W35: 0 | X35: 0 | Y35: 0 | Z35: 35.29 | AA35: 0 | AB35: 1 | AC35: 1 | AD35: 0 | AE35: 0 | AF35: 0 | AG35: 0 | AH35: 0 | AI35: 0 | AJ35: 0 | AK35: 0 | AL35: 0 | AM35: 0 | AN35: 0 | AO35: 0 | AP35: 0 | AQ35: 0 | AR35: 0 | AS35: 0 | AT35: =VLOOKUP(H35,Control!B:C,2,0) -> 5 | AV35: =IFERROR(VLOOKUP($B35,'[1]Accounts - MDM Data'!$N$1:$O$5,2,0),$B35) -> Deal 4 | AW35: =VLOOKUP(H35,'[1]Accounts - MDM Data'!$H$2:$I$8,2,FALSE) -> #N/A | AX35: =N35 -> 0 | AY35: =P35 -> 0 | AZ35: =Q35 -> 0 | BA35: =R35 -> 0 | BB35: =T35 -> 35.29 | BC35: =S35+U35 -> 0 | BD35: =SUM(AD35:AF35) -> 0 | BE35: =SUM(AG35:AI35) -> 0 | BF35: =IF($M35="Yes",0,IF(ISNUMBER(SEARCH("LH",F35)),SUM($AM35+$AN35),IF($N35=0,SUM(AF35+AG35+AH35+AM35+AN35),$N35))) -> 0 | BG35: =IF($M35="Yes",0,IF(ISNUMBER(SEARCH("LH",F35)),$AL35,IF(SUM($P35:$S35)=0,SUM(AE35+AI35+AL35),SUM($P35:$S35)))) -> 0 | BH35: =IF(M35="yes",0,IF(ISNUMBER(SEARCH("LH",F35)),AK35,IF(SUM(T35+U35)=0,SUM(AD35+AK35),SUM(T35+U35)))) -> 35.29 | BI35: =ROUND(SUM($AP35:$AS35),2) -> 0 | BJ35: =SUM(BD35:BH35)+SUM(AO35:AS35)+O35 -> 35.29 | BK35: =ROUND($AX35/$AB35,2) -> 0 | BL35: =ROUND(SUM($AY35:$BA35)/$AC35+($AX35/$AC35-$BK35),2) -> 0 | BM35: =ROUND($BB35/$AC35,2) -> 35.29 | BN35: =ROUND($BC35/$AC35,2) -> 0 | BO35: =ROUND($BF35/AB35,2) -> 0 | BP35: =ROUND(IF($BL35=0,0,$BL35+IF($S35=0,0,$BN35)),2) -> 0 | BQ35: =ROUND(IF($BM35=0,0,$BM35+IF($U35=0,0,$BN35)),2) -> 35.29 | BR35: =ROUND(SUM($AP35:$AS35)/$AC35,2) -> 0 | BS35: =SUM(BO35:BR35) -> 35.29 | BU35: =SUM(AD35:AG35)+SUM(BF35:BH35) -> 35.29 | BV35: =SUM(N35:U35) -> 35.29 | BW35: =SUM(AP35:AS35) -> 0 | BX35: =SUM(AD35,AE35,AF35) -> 0 | BY35: =BU35-BV35 -> 0 | BZ35: =N35+P35+Q35+R35+S35+T35+U35 -> 35.29 | CA35: Domestic | CB35: =IF(SUM(AD35:AJ35)=0,"Equity","Debt") -> Equity | CC35: =IF(RIGHT(CV35,4)="(GP)","General Partners",IF(RIGHT(CV35,5)="(ALP)","GP Excess",CV35)) -> LP SCH A 5 | CD35: =F35&"_"&AV35 -> SCH A Legal Entity 4_Deal 4 | CE35: =B35&"_"&G35&"_"&E35 -> Deal 4_Partner 5_Partnership 2 | CF35: =IFERROR(VLOOKUP(CE35,[1]Mapping!A:E,5,0),"") | CG35: Deal 4 | CO35: =IF(FM35<>"",FM35,FJ35) -> 0 | CV35: LP SCH A 5 | CX35: Deal 4
A36: 45382 | B36: =IFERROR(VLOOKUP(CG36,CH:CI,2,0),CG36) -> Deal 4 | C36: Tranche 7 | D36: Position 7 | E36: Partnership 2 | F36: SCH A Legal Entity 4 | G36: Partner 7 | H36: =IF(CF36<>"",CF36,CC36) -> LP SCH A 7 | I36: Partner ID 4 | J36: USD | K36: Vehicle 4 | L36: Income | N36: 0 | O36: 0 | P36: 0 | Q36: 0 | R36: 0 | S36: 0 | T36: 31.12 | U36: 0 | V36: 0 | W36: 0 | X36: 0 | Y36: 0 | Z36: 31.12 | AA36: 0 | AB36: 1 | AC36: 1 | AD36: 0 | AE36: 0 | AF36: 0 | AG36: 0 | AH36: 0 | AI36: 0 | AJ36: 0 | AK36: 0 | AL36: 0 | AM36: 0 | AN36: 0 | AO36: 0 | AP36: 0 | AQ36: 0 | AR36: 0 | AS36: 0 | AT36: =VLOOKUP(H36,Control!B:C,2,0) -> 7 | AV36: =IFERROR(VLOOKUP($B36,'[1]Accounts - MDM Data'!$N$1:$O$5,2,0),$B36) -> Deal 4 | AW36: =VLOOKUP(H36,'[1]Accounts - MDM Data'!$H$2:$I$8,2,FALSE) -> #N/A | AX36: =N36 -> 0 | AY36: =P36 -> 0 | AZ36: =Q36 -> 0 | BA36: =R36 -> 0 | BB36: =T36 -> 31.12 | BC36: =S36+U36 -> 0 | BD36: =SUM(AD36:AF36) -> 0 | BE36: =SUM(AG36:AI36) -> 0 | BF36: =IF($M36="Yes",0,IF(ISNUMBER(SEARCH("LH",F36)),SUM($AM36+$AN36),IF($N36=0,SUM(AF36+AG36+AH36+AM36+AN36),$N36))) -> 0 | BG36: =IF($M36="Yes",0,IF(ISNUMBER(SEARCH("LH",F36)),$AL36,IF(SUM($P36:$S36)=0,SUM(AE36+AI36+AL36),SUM($P36:$S36)))) -> 0 | BH36: =IF(M36="yes",0,IF(ISNUMBER(SEARCH("LH",F36)),AK36,IF(SUM(T36+U36)=0,SUM(AD36+AK36),SUM(T36+U36)))) -> 31.12 | BI36: =ROUND(SUM($AP36:$AS36),2) -> 0 | BJ36: =SUM(BD36:BH36)+SUM(AO36:AS36)+O36 -> 31.12 | BK36: =ROUND($AX36/$AB36,2) -> 0 | BL36: =ROUND(SUM($AY36:$BA36)/$AC36+($AX36/$AC36-$BK36),2) -> 0 | BM36: =ROUND($BB36/$AC36,2) -> 31.12 | BN36: =ROUND($BC36/$AC36,2) -> 0 | BO36: =ROUND($BF36/AB36,2) -> 0 | BP36: =ROUND(IF($BL36=0,0,$BL36+IF($S36=0,0,$BN36)),2) -> 0 | BQ36: =ROUND(IF($BM36=0,0,$BM36+IF($U36=0,0,$BN36)),2) -> 31.12 | BR36: =ROUND(SUM($AP36:$AS36)/$AC36,2) -> 0 | BS36: =SUM(BO36:BR36) -> 31.12 | BU36: =SUM(AD36:AG36)+SUM(BF36:BH36) -> 31.12 | BV36: =SUM(N36:U36) -> 31.12 | BW36: =SUM(AP36:AS36) -> 0 | BX36: =SUM(AD36,AE36,AF36) -> 0 | BY36: =BU36-BV36 -> 0 | BZ36: =N36+P36+Q36+R36+S36+T36+U36 -> 31.12 | CA36: Domestic | CB36: =IF(SUM(AD36:AJ36)=0,"Equity","Debt") -> Equity | CC36: =IF(RIGHT(CV36,4)="(GP)","General Partners",IF(RIGHT(CV36,5)="(ALP)","GP Excess",CV36)) -> LP SCH A 7 | CD36: =F36&"_"&AV36 -> SCH A Legal Entity 4_Deal 4 | CE36: =B36&"_"&G36&"_"&E36 -> Deal 4_Partner 7_Partnership 2 | CF36: =IFERROR(VLOOKUP(CE36,[1]Mapping!A:E,5,0),"") | CG36: Deal 4 | CO36: =IF(FM36<>"",FM36,FJ36) -> 0 | CV36: LP SCH A 7 | CX36: Deal 4
A37: 45382 | B37: =IFERROR(VLOOKUP(CG37,CH:CI,2,0),CG37) -> Deal 4 | C37: Tranche 6 | D37: Position 6 | E37: Partnership 13 | F37: SCH A Legal Entity 14 | G37: Partner 2 | H37: =IF(CF37<>"",CF37,CC37) -> LP SCH A 2 | I37: Partner ID 14 | J37: USD | K37: Vehicle 14 | L37: Income | N37: 0 | O37: 0 | P37: 0 | Q37: 0 | R37: 0 | S37: 0 | T37: 605.04 | U37: 0 | V37: 0 | W37: 0 | X37: 0 | Y37: 0 | Z37: 605.04 | AA37: 0 | AB37: 1 | AC37: 1 | AD37: 0 | AE37: 0 | AF37: 0 | AG37: 0 | AH37: 0 | AI37: 0 | AJ37: 0 | AK37: 0 | AL37: 0 | AM37: 0 | AN37: 0 | AO37: 0 | AP37: 0 | AQ37: 0 | AR37: 0 | AS37: 0 | AT37: =VLOOKUP(H37,Control!B:C,2,0) -> 2 | AV37: =IFERROR(VLOOKUP($B37,'[1]Accounts - MDM Data'!$N$1:$O$5,2,0),$B37) -> Deal 4 | AW37: =VLOOKUP(H37,'[1]Accounts - MDM Data'!$H$2:$I$8,2,FALSE) -> #N/A | AX37: =N37 -> 0 | AY37: =P37 -> 0 | AZ37: =Q37 -> 0 | BA37: =R37 -> 0 | BB37: =T37 -> 605.04 | BC37: =S37+U37 -> 0 | BD37: =SUM(AD37:AF37) -> 0 | BE37: =SUM(AG37:AI37) -> 0 | BF37: =IF($M37="Yes",0,IF(ISNUMBER(SEARCH("LH",F37)),SUM($AM37+$AN37),IF($N37=0,SUM(AF37+AG37+AH37+AM37+AN37),$N37))) -> 0 | BG37: =IF($M37="Yes",0,IF(ISNUMBER(SEARCH("LH",F37)),$AL37,IF(SUM($P37:$S37)=0,SUM(AE37+AI37+AL37),SUM($P37:$S37)))) -> 0 | BH37: =IF(M37="yes",0,IF(ISNUMBER(SEARCH("LH",F37)),AK37,IF(SUM(T37+U37)=0,SUM(AD37+AK37),SUM(T37+U37)))) -> 605.04 | BI37: =ROUND(SUM($AP37:$AS37),2) -> 0 | BJ37: =SUM(BD37:BH37)+SUM(AO37:AS37)+O37 -> 605.04 | BK37: =ROUND($AX37/$AB37,2) -> 0 | BL37: =ROUND(SUM($AY37:$BA37)/$AC37+($AX37/$AC37-$BK37),2) -> 0 | BM37: =ROUND($BB37/$AC37,2) -> 605.04 | BN37: =ROUND($BC37/$AC37,2) -> 0 | BO37: =ROUND($BF37/AB37,2) -> 0 | BP37: =ROUND(IF($BL37=0,0,$BL37+IF($S37=0,0,$BN37)),2) -> 0 | BQ37: =ROUND(IF($BM37=0,0,$BM37+IF($U37=0,0,$BN37)),2) -> 605.04 | BR37: =ROUND(SUM($AP37:$AS37)/$AC37,2) -> 0 | BS37: =SUM(BO37:BR37) -> 605.04 | BU37: =SUM(AD37:AG37)+SUM(BF37:BH37) -> 605.04 | BV37: =SUM(N37:U37) -> 605.04 | BW37: =SUM(AP37:AS37) -> 0 | BX37: =SUM(AD37,AE37,AF37) -> 0 | BY37: =BU37-BV37 -> 0 | BZ37: =N37+P37+Q37+R37+S37+T37+U37 -> 605.04 | CA37: Domestic | CB37: =IF(SUM(AD37:AJ37)=0,"Equity","Debt") -> Equity | CC37: =IF(RIGHT(CV37,4)="(GP)","General Partners",IF(RIGHT(CV37,5)="(ALP)","GP Excess",CV37)) -> LP SCH A 2 | CD37: =F37&"_"&AV37 -> SCH A Legal Entity 14_Deal 4 | CE37: =B37&"_"&G37&"_"&E37 -> Deal 4_Partner 2_Partnership 13 | CF37: =IFERROR(VLOOKUP(CE37,[1]Mapping!A:E,5,0),"") | CG37: Deal 4 | CO37: =IF(FM37<>"",FM37,FJ37) -> 0 | CV37: LP SCH A 2 | CX37: Deal 4
A38: 45382 | B38: =IFERROR(VLOOKUP(CG38,CH:CI,2,0),CG38) -> Deal 4 | C38: Tranche 8 | D38: Position 8 | E38: Partnership 14 | F38: SCH A Legal Entity 15 | G38: Partner 3 | H38: =IF(CF38<>"",CF38,CC38) -> LP SCH A 3 | I38: Partner ID 15 | J38: USD | K38: Vehicle 15 | L38: Income | N38: 0 | O38: 0 | P38: 0 | Q38: 0 | R38: 0 | S38: 0 | T38: 782.02 | U38: 0 | V38: 0 | W38: 0 | X38: 0 | Y38: 0 | Z38: 782.02 | AA38: 0 | AB38: 1 | AC38: 1 | AD38: 0 | AE38: 0 | AF38: 0 | AG38: 0 | AH38: 0 | AI38: 0 | AJ38: 0 | AK38: 0 | AL38: 0 | AM38: 0 | AN38: 0 | AO38: 0 | AP38: 0 | AQ38: 0 | AR38: 0 | AS38: 0 | AT38: =VLOOKUP(H38,Control!B:C,2,0) -> 3 | AV38: =IFERROR(VLOOKUP($B38,'[1]Accounts - MDM Data'!$N$1:$O$5,2,0),$B38) -> Deal 4 | AW38: =VLOOKUP(H38,'[1]Accounts - MDM Data'!$H$2:$I$8,2,FALSE) -> #N/A | AX38: =N38 -> 0 | AY38: =P38 -> 0 | AZ38: =Q38 -> 0 | BA38: =R38 -> 0 | BB38: =T38 -> 782.02 | BC38: =S38+U38 -> 0 | BD38: =SUM(AD38:AF38) -> 0 | BE38: =SUM(AG38:AI38) -> 0 | BF38: =IF($M38="Yes",0,IF(ISNUMBER(SEARCH("LH",F38)),SUM($AM38+$AN38),IF($N38=0,SUM(AF38+AG38+AH38+AM38+AN38),$N38))) -> 0 | BG38: =IF($M38="Yes",0,IF(ISNUMBER(SEARCH("LH",F38)),$AL38,IF(SUM($P38:$S38)=0,SUM(AE38+AI38+AL38),SUM($P38:$S38)))) -> 0 | BH38: =IF(M38="yes",0,IF(ISNUMBER(SEARCH("LH",F38)),AK38,IF(SUM(T38+U38)=0,SUM(AD38+AK38),SUM(T38+U38)))) -> 782.02 | BI38: =ROUND(SUM($AP38:$AS38),2) -> 0 | BJ38: =SUM(BD38:BH38)+SUM(AO38:AS38)+O38 -> 782.02 | BK38: =ROUND($AX38/$AB38,2) -> 0 | BL38: =ROUND(SUM($AY38:$BA38)/$AC38+($AX38/$AC38-$BK38),2) -> 0 | BM38: =ROUND($BB38/$AC38,2) -> 782.02 | BN38: =ROUND($BC38/$AC38,2) -> 0 | BO38: =ROUND($BF38/AB38,2) -> 0 | BP38: =ROUND(IF($BL38=0,0,$BL38+IF($S38=0,0,$BN38)),2) -> 0 | BQ38: =ROUND(IF($BM38=0,0,$BM38+IF($U38=0,0,$BN38)),2) -> 782.02 | BR38: =ROUND(SUM($AP38:$AS38)/$AC38,2) -> 0 | BS38: =SUM(BO38:BR38) -> 782.02 | BU38: =SUM(AD38:AG38)+SUM(BF38:BH38) -> 782.02 | BV38: =SUM(N38:U38) -> 782.02 | BW38: =SUM(AP38:AS38) -> 0 | BX38: =SUM(AD38,AE38,AF38) -> 0 | BY38: =BU38-BV38 -> 0 | BZ38: =N38+P38+Q38+R38+S38+T38+U38 -> 782.02 | CA38: Domestic | CB38: =IF(SUM(AD38:AJ38)=0,"Equity","Debt") -> Equity | CC38: =IF(RIGHT(CV38,4)="(GP)","General Partners",IF(RIGHT(CV38,5)="(ALP)","GP Excess",CV38)) -> LP SCH A 3 | CD38: =F38&"_"&AV38 -> SCH A Legal Entity 15_Deal 4 | CE38: =B38&"_"&G38&"_"&E38 -> Deal 4_Partner 3_Partnership 14 | CF38: =IFERROR(VLOOKUP(CE38,[1]Mapping!A:E,5,0),"") | CG38: Deal 4 | CO38: =IF(FM38<>"",FM38,FJ38) -> 0 | CV38: LP SCH A 3 | CX38: Deal 4
A39: 45382 | B39: =IFERROR(VLOOKUP(CG39,CH:CI,2,0),CG39) -> Deal 4 | C39: Tranche 6 | D39: Position 6 | E39: Partnership 14 | F39: SCH A Legal Entity 15 | G39: Partner 3 | H39: =IF(CF39<>"",CF39,CC39) -> LP SCH A 3 | I39: Partner ID 15 | J39: USD | K39: Vehicle 15 | L39: Income | N39: 0 | O39: 0 | P39: 0 | Q39: 0 | R39: 0 | S39: 0 | T39: 207.65 | U39: 0 | V39: 0 | W39: 0 | X39: 0 | Y39: 0 | Z39: 207.65 | AA39: 0 | AB39: 1 | AC39: 1 | AD39: 0 | AE39: 0 | AF39: 0 | AG39: 0 | AH39: 0 | AI39: 0 | AJ39: 0 | AK39: 0 | AL39: 0 | AM39: 0 | AN39: 0 | AO39: 0 | AP39: -62.3 | AQ39: 0 | AR39: 0 | AS39: 0 | AT39: =VLOOKUP(H39,Control!B:C,2,0) -> 3 | AV39: =IFERROR(VLOOKUP($B39,'[1]Accounts - MDM Data'!$N$1:$O$5,2,0),$B39) -> Deal 4 | AW39: =VLOOKUP(H39,'[1]Accounts - MDM Data'!$H$2:$I$8,2,FALSE) -> #N/A | AX39: =N39 -> 0 | AY39: =P39 -> 0 | AZ39: =Q39 -> 0 | BA39: =R39 -> 0 | BB39: =T39 -> 207.65 | BC39: =S39+U39 -> 0 | BD39: =SUM(AD39:AF39) -> 0 | BE39: =SUM(AG39:AI39) -> 0 | BF39: =IF($M39="Yes",0,IF(ISNUMBER(SEARCH("LH",F39)),SUM($AM39+$AN39),IF($N39=0,SUM(AF39+AG39+AH39+AM39+AN39),$N39))) -> 0 | BG39: =IF($M39="Yes",0,IF(ISNUMBER(SEARCH("LH",F39)),$AL39,IF(SUM($P39:$S39)=0,SUM(AE39+AI39+AL39),SUM($P39:$S39)))) -> 0 | BH39: =IF(M39="yes",0,IF(ISNUMBER(SEARCH("LH",F39)),AK39,IF(SUM(T39+U39)=0,SUM(AD39+AK39),SUM(T39+U39)))) -> 207.65 | BI39: =ROUND(SUM($AP39:$AS39),2) -> -62.3 | BJ39: =SUM(BD39:BH39)+SUM(AO39:AS39)+O39 -> 145.35 | BK39: =ROUND($AX39/$AB39,2) -> 0 | BL39: =ROUND(SUM($AY39:$BA39)/$AC39+($AX39/$AC39-$BK39),2) -> 0 | BM39: =ROUND($BB39/$AC39,2) -> 207.65 | BN39: =ROUND($BC39/$AC39,2) -> 0 | BO39: =ROUND($BF39/AB39,2) -> 0 | BP39: =ROUND(IF($BL39=0,0,$BL39+IF($S39=0,0,$BN39)),2) -> 0 | BQ39: =ROUND(IF($BM39=0,0,$BM39+IF($U39=0,0,$BN39)),2) -> 207.65 | BR39: =ROUND(SUM($AP39:$AS39)/$AC39,2) -> -62.3 | BS39: =SUM(BO39:BR39) -> 145.35 | BU39: =SUM(AD39:AG39)+SUM(BF39:BH39) -> 207.65 | BV39: =SUM(N39:U39) -> 207.65 | BW39: =SUM(AP39:AS39) -> -62.3 | BX39: =SUM(AD39,AE39,AF39) -> 0 | BY39: =BU39-BV39 -> 0 | BZ39: =N39+P39+Q39+R39+S39+T39+U39 -> 207.65 | CA39: Domestic | CB39: =IF(SUM(AD39:AJ39)=0,"Equity","Debt") -> Equity | CC39: =IF(RIGHT(CV39,4)="(GP)","General Partners",IF(RIGHT(CV39,5)="(ALP)","GP Excess",CV39)) -> LP SCH A 3 | CD39: =F39&"_"&AV39 -> SCH A Legal Entity 15_Deal 4 | CE39: =B39&"_"&G39&"_"&E39 -> Deal 4_Partner 3_Partnership 14 | CF39: =IFERROR(VLOOKUP(CE39,[1]Mapping!A:E,5,0),"") | CG39: Deal 4 | CO39: =IF(FM39<>"",FM39,FJ39) -> 0 | CV39: LP SCH A 3 | CX39: Deal 4
A40: 45382 | B40: =IFERROR(VLOOKUP(CG40,CH:CI,2,0),CG40) -> Deal 4 | C40: Tranche 6 | D40: Position 6 | E40: Partnership 3 | F40: SCH A Legal Entity 5 | G40: Partner 6 | H40: =IF(CF40<>"",CF40,CC40) -> LP SCH A 6 | I40: Partner ID 5 | J40: USD | K40: Vehicle 5 | L40: Income | N40: 0 | O40: 0 | P40: 0 | Q40: 0 | R40: 0 | S40: 0 | T40: 42.35 | U40: 0 | V40: 0 | W40: 0 | X40: 0 | Y40: 0 | Z40: 42.35 | AA40: 0 | AB40: 1 | AC40: 1 | AD40: 0 | AE40: 0 | AF40: 0 | AG40: 0 | AH40: 0 | AI40: 0 | AJ40: 0 | AK40: 0 | AL40: 0 | AM40: 0 | AN40: 0 | AO40: 0 | AP40: 0 | AQ40: 0 | AR40: 0 | AS40: 0 | AT40: =VLOOKUP(H40,Control!B:C,2,0) -> 6 | AV40: =IFERROR(VLOOKUP($B40,'[1]Accounts - MDM Data'!$N$1:$O$5,2,0),$B40) -> Deal 4 | AW40: =VLOOKUP(H40,'[1]Accounts - MDM Data'!$H$2:$I$8,2,FALSE) -> #N/A | AX40: =N40 -> 0 | AY40: =P40 -> 0 | AZ40: =Q40 -> 0 | BA40: =R40 -> 0 | BB40: =T40 -> 42.35 | BC40: =S40+U40 -> 0 | BD40: =SUM(AD40:AF40) -> 0 | BE40: =SUM(AG40:AI40) -> 0 | BF40: =IF($M40="Yes",0,IF(ISNUMBER(SEARCH("LH",F40)),SUM($AM40+$AN40),IF($N40=0,SUM(AF40+AG40+AH40+AM40+AN40),$N40))) -> 0 | BG40: =IF($M40="Yes",0,IF(ISNUMBER(SEARCH("LH",F40)),$AL40,IF(SUM($P40:$S40)=0,SUM(AE40+AI40+AL40),SUM($P40:$S40)))) -> 0 | BH40: =IF(M40="yes",0,IF(ISNUMBER(SEARCH("LH",F40)),AK40,IF(SUM(T40+U40)=0,SUM(AD40+AK40),SUM(T40+U40)))) -> 42.35 | BI40: =ROUND(SUM($AP40:$AS40),2) -> 0 | BJ40: =SUM(BD40:BH40)+SUM(AO40:AS40)+O40 -> 42.35 | BK40: =ROUND($AX40/$AB40,2) -> 0 | BL40: =ROUND(SUM($AY40:$BA40)/$AC40+($AX40/$AC40-$BK40),2) -> 0 | BM40: =ROUND($BB40/$AC40,2) -> 42.35 | BN40: =ROUND($BC40/$AC40,2) -> 0 | BO40: =ROUND($BF40/AB40,2) -> 0 | BP40: =ROUND(IF($BL40=0,0,$BL40+IF($S40=0,0,$BN40)),2) -> 0 | BQ40: =ROUND(IF($BM40=0,0,$BM40+IF($U40=0,0,$BN40)),2) -> 42.35 | BR40: =ROUND(SUM($AP40:$AS40)/$AC40,2) -> 0 | BS40: =SUM(BO40:BR40) -> 42.35 | BU40: =SUM(AD40:AG40)+SUM(BF40:BH40) -> 42.35 | BV40: =SUM(N40:U40) -> 42.35 | BW40: =SUM(AP40:AS40) -> 0 | BX40: =SUM(AD40,AE40,AF40) -> 0 | BY40: =BU40-BV40 -> 0 | BZ40: =N40+P40+Q40+R40+S40+T40+U40 -> 42.35 | CA40: Domestic | CB40: =IF(SUM(AD40:AJ40)=0,"Equity","Debt") -> Equity | CC40: =IF(RIGHT(CV40,4)="(GP)","General Partners",IF(RIGHT(CV40,5)="(ALP)","GP Excess",CV40)) -> LP SCH A 6 | CD40: =F40&"_"&AV40 -> SCH A Legal Entity 5_Deal 4 | CE40: =B40&"_"&G40&"_"&E40 -> Deal 4_Partner 6_Partnership 3 | CF40: =IFERROR(VLOOKUP(CE40,[1]Mapping!A:E,5,0),"") | CG40: Deal 4 | CO40: =IF(FM40<>"",FM40,FJ40) -> 0 | CV40: LP SCH A 6 | CX40: Deal 4
... A206: 45382 | B206: =IFERROR(VLOOKUP(CG206,CH:CI,2,0),CG206) -> Deal 9 | C206: Tranche 19 | D206: Position 19 | E206: Partnership 17 | F206: SCH A Legal Entity 23 | G206: Partner 7 | H206: =IF(CF206<>"",CF206,CC206) -> LP SCH A 7 | I206: Partner ID 23 | J206: USD | K206: Vehicle 23 | L206: Income | N206: 0 | O206: 0 | P206: 0 | Q206: 0 | R206: 0 | S206: 0 | T206: 41.51 | U206: 0 | V206: 0 | W206: 0 | X206: 0 | Y206: 0 | Z206: 41.51 | AA206: 0 | AB206: 1 | AC206: 1 | AD206: 0 | AE206: 0 | AF206: 0 | AG206: 0 | AH206: 0 | AI206: 0 | AJ206: 0 | AK206: 0 | AL206: 0 | AM206: 0 | AN206: 0 | AO206: 0 | AP206: 0 | AQ206: 0 | AR206: 0 | AS206: 0 | AT206: =VLOOKUP(H206,Control!B:C,2,0) -> 7 | AV206: =IFERROR(VLOOKUP($B206,'[1]Accounts - MDM Data'!$N$1:$O$5,2,0),$B206) -> Deal 9 | AW206: =VLOOKUP(H206,'[1]Accounts - MDM Data'!$H$2:$I$8,2,FALSE) -> #N/A | AX206: =N206 -> 0 | AY206: =P206 -> 0 | AZ206: =Q206 -> 0 | BA206: =R206 -> 0 | BB206: =T206 -> 41.51 | BC206: =S206+U206 -> 0 | BD206: =SUM(AD206:AF206) -> 0 | BE206: =SUM(AG206:AI206) -> 0 | BF206: =IF($M206="Yes",0,IF(ISNUMBER(SEARCH("LH",F206)),SUM($AM206+$AN206),IF($N206=0,SUM(AF206+AG206+AH206+AM206+AN206),$N206))) -> 0 | BG206: =IF($M206="Yes",0,IF(ISNUMBER(SEARCH("LH",F206)),$AL206,IF(SUM($P206:$S206)=0,SUM(AE206+AI206+AL206),SUM($P206:$S206)))) -> 0 | BH206: =IF(M206="yes",0,IF(ISNUMBER(SEARCH("LH",F206)),AK206,IF(SUM(T206+U206)=0,SUM(AD206+AK206),SUM(T206+U206)))) -> 41.51 | BI206: =ROUND(SUM($AP206:$AS206),2) -> 0 | BJ206: =SUM(BD206:BH206)+SUM(AO206:AS206)+O206 -> 41.51 | BK206: =ROUND($AX206/$AB206,2) -> 0 | BL206: =ROUND(SUM($AY206:$BA206)/$AC206+($AX206/$AC206-$BK206),2) -> 0 | BM206: =ROUND($BB206/$AC206,2) -> 41.51 | BN206: =ROUND($BC206/$AC206,2) -> 0 | BO206: =ROUND($BF206/AB206,2) -> 0 | BP206: =ROUND(IF($BL206=0,0,$BL206+IF($S206=0,0,$BN206)),2) -> 0 | BQ206: =ROUND(IF($BM206=0,0,$BM206+IF($U206=0,0,$BN206)),2) -> 41.51 | BR206: =ROUND(SUM($AP206:$AS206)/$AC206,2) -> 0 | BS206: =SUM(BO206:BR206) -> 41.51 | BU206: =SUM(AD206:AG206)+SUM(BF206:BH206) -> 41.51 | BV206: =SUM(N206:U206) -> 41.51 | BW206: =SUM(AP206:AS206) -> 0 | BX206: =SUM(AD206,AE206,AF206) -> 0 | BY206: =BU206-BV206 -> 0 | BZ206: =N206+P206+Q206+R206+S206+T206+U206 -> 41.51 | CA206: Domestic | CB206: =IF(SUM(AD206:AJ206)=0,"Equity","Debt") -> Equity | CC206: =IF(RIGHT(CV206,4)="(GP)","General Partners",IF(RIGHT(CV206,5)="(ALP)","GP Excess",CV206)) -> LP SCH A 7 | CD206: =F206&"_"&AV206 -> SCH A Legal Entity 23_Deal 9 | CE206: =B206&"_"&G206&"_"&E206 -> Deal 9_Partner 7_Partnership 17 | CF206: =IFERROR(VLOOKUP(CE206,[1]Mapping!A:E,5,0),"") | CG206: Deal 9 | CO206: =IF(FM206<>"",FM206,FJ206) -> 0 | CV206: LP SCH A 7 | CX206: Deal 9

Sheet Control
B1: Row Labels
B2: LP SCH A 1 | C2: {=_xlfn.IFS(VLOOKUP(B2,Datadump!H:H,1,0)=Control!$B$2,1,VLOOKUP(B2,Datadump!H:H,1,0)=Control!$B$3,2,VLOOKUP(B2,Datadump!H:H,1,0)=Control!$B$4,3,VLOOKUP(B2,Datadump!H:H,1,0)=Control!$B$5,4,VLOOKUP(B2,Datadump!H:H,1,0)=Control!$B$6,5,VLOOKUP(B2,Datadump!H:H,1,0)=Control!$B$7,6,VLOOKUP(B2,Datadump!H:H,1,0)=Control!$B$7,6)} -> 1
B3: LP SCH A 2 | C3: {=_xlfn.IFS(VLOOKUP(B3,Datadump!H:H,1,0)=Control!$B$2,1,VLOOKUP(B3,Datadump!H:H,1,0)=Control!$B$3,2,VLOOKUP(B3,Datadump!H:H,1,0)=Control!$B$4,3,VLOOKUP(B3,Datadump!H:H,1,0)=Control!$B$5,4,VLOOKUP(B3,Datadump!H:H,1,0)=Control!$B$6,5,VLOOKUP(B3,Datadump!H:H,1,0)=Control!$B$7,6,VLOOKUP(B3,Datadump!H:H,1,0)=Control!$B$7,6)} -> 2
B4: LP SCH A 3 | C4: {=_xlfn.IFS(VLOOKUP(B4,Datadump!H:H,1,0)=Control!$B$2,1,VLOOKUP(B4,Datadump!H:H,1,0)=Control!$B$3,2,VLOOKUP(B4,Datadump!H:H,1,0)=Control!$B$4,3,VLOOKUP(B4,Datadump!H:H,1,0)=Control!$B$5,4,VLOOKUP(B4,Datadump!H:H,1,0)=Control!$B$6,5,VLOOKUP(B4,Datadump!H:H,1,0)=Control!$B$7,6,VLOOKUP(B4,Datadump!H:H,1,0)=Control!$B$7,6)} -> 3
B5: LP SCH A 4 | C5: {=_xlfn.IFS(VLOOKUP(B5,Datadump!H:H,1,0)=Control!$B$2,1,VLOOKUP(B5,Datadump!H:H,1,0)=Control!$B$3,2,VLOOKUP(B5,Datadump!H:H,1,0)=Control!$B$4,3,VLOOKUP(B5,Datadump!H:H,1,0)=Control!$B$5,4,VLOOKUP(B5,Datadump!H:H,1,0)=Control!$B$6,5,VLOOKUP(B5,Datadump!H:H,1,0)=Control!$B$7,6,VLOOKUP(B5,Datadump!H:H,1,0)=Control!$B$7,6)} -> 4
B6: LP SCH A 5 | C6: {=_xlfn.IFS(VLOOKUP(B6,Datadump!H:H,1,0)=Control!$B$2,1,VLOOKUP(B6,Datadump!H:H,1,0)=Control!$B$3,2,VLOOKUP(B6,Datadump!H:H,1,0)=Control!$B$4,3,VLOOKUP(B6,Datadump!H:H,1,0)=Control!$B$5,4,VLOOKUP(B6,Datadump!H:H,1,0)=Control!$B$6,5,VLOOKUP(B6,Datadump!H:H,1,0)=Control!$B$7,6,VLOOKUP(B6,Datadump!H:H,1,0)=Control!$B$7,6)} -> 5
B7: LP SCH A 6 | C7: {=_xlfn.IFS(VLOOKUP(B7,Datadump!H:H,1,0)=Control!$B$2,1,VLOOKUP(B7,Datadump!H:H,1,0)=Control!$B$3,2,VLOOKUP(B7,Datadump!H:H,1,0)=Control!$B$4,3,VLOOKUP(B7,Datadump!H:H,1,0)=Control!$B$5,4,VLOOKUP(B7,Datadump!H:H,1,0)=Control!$B$6,5,VLOOKUP(B7,Datadump!H:H,1,0)=Control!$B$7,6,VLOOKUP(B7,Datadump!H:H,1,0)=Control!$B$7,6)} -> 6
B8: LP SCH A 7 | C8: {=_xlfn.IFS(VLOOKUP(B8,Datadump!H:H,1,0)=Control!$B$2,1,VLOOKUP(B8,Datadump!H:H,1,0)=Control!$B$3,2,VLOOKUP(B8,Datadump!H:H,1,0)=Control!$B$4,3,VLOOKUP(B8,Datadump!H:H,1,0)=Control!$B$5,4,VLOOKUP(B8,Datadump!H:H,1,0)=Control!$B$6,5,VLOOKUP(B8,Datadump!H:H,1,0)=Control!$B$7,6,VLOOKUP(B8,Datadump!H:H,1,0)=Control!$B$7,6,VLOOKUP(B8,Datadump!H:H,1,0)=Control!$B$8,7)} -> 7
B9: Grand Total
